[
	{
		"id" : 394096,
		"serial_reference" : "4612303W1A     ",
		"short_code" : "PTM",
		"date_created" : "2021-11-09 06:36:38",
		"last_updated" : "2021-11-09 06:36:38"
	},
	{
		"id" : 394104,
		"serial_reference" : "462717990A     ",
		"short_code" : "PTM",
		"date_created" : "2021-11-09 06:55:40",
		"last_updated" : "2021-11-09 06:55:40"
	},
	{
		"id" : 394128,
		"serial_reference" : "265572U000     ",
		"short_code" : "PTM",
		"date_created" : "2021-11-09 07:30:55",
		"last_updated" : "2021-11-09 07:30:55"
	},
	{
		"id" : 394144,
		"serial_reference" : "1643917B0A     ",
		"short_code" : "PTM",
		"date_created" : "2021-11-09 07:37:47",
		"last_updated" : "2021-11-09 07:37:47"
	},
	{
		"id" : 394152,
		"serial_reference" : "442514CA0BRP",
		"short_code" : "CTD",
		"date_created" : "2021-11-09 07:50:34",
		"last_updated" : "2021-11-09 07:50:34"
	},
	{
		"id" : 394160,
		"serial_reference" : "442504CA0BRP",
		"short_code" : "CTD",
		"date_created" : "2021-11-09 07:53:01",
		"last_updated" : "2021-11-09 07:53:01"
	},
	{
		"id" : 394168,
		"serial_reference" : "442504CA0BRP",
		"short_code" : "CTD",
		"date_created" : "2021-11-09 07:55:43",
		"last_updated" : "2021-11-09 07:55:43"
	},
	{
		"id" : 394176,
		"serial_reference" : "442504CA0BRP",
		"short_code" : "CTD",
		"date_created" : "2021-11-09 07:56:16",
		"last_updated" : "2021-11-09 07:56:16"
	},
	{
		"id" : 394192,
		"serial_reference" : "240126WK6C",
		"short_code" : "PTM",
		"date_created" : "2021-11-09 08:17:18",
		"last_updated" : "2021-11-09 08:17:18"
	},
	{
		"id" : 394200,
		"serial_reference" : "240126WK6A",
		"short_code" : "PTM",
		"date_created" : "2021-11-09 08:17:18",
		"last_updated" : "2021-11-09 08:17:18"
	},
	{
		"id" : 394208,
		"serial_reference" : "240126WK8A",
		"short_code" : "PTM",
		"date_created" : "2021-11-09 08:17:19",
		"last_updated" : "2021-11-09 08:17:19"
	},
	{
		"id" : 394216,
		"serial_reference" : "240126WK6A",
		"short_code" : "PTM",
		"date_created" : "2021-11-09 08:17:19",
		"last_updated" : "2021-11-09 08:17:19"
	},
	{
		"id" : 394248,
		"serial_reference" : "233000290R",
		"short_code" : "CTS",
		"date_created" : "2021-11-09 08:24:15",
		"last_updated" : "2021-11-09 08:24:15"
	},
	{
		"id" : 394264,
		"serial_reference" : "442514CA0BRP",
		"short_code" : "CTD",
		"date_created" : "2021-11-09 08:39:10",
		"last_updated" : "2021-11-09 08:39:10"
	},
	{
		"id" : 394272,
		"serial_reference" : "442504CA0BRP",
		"short_code" : "CTD",
		"date_created" : "2021-11-09 08:41:01",
		"last_updated" : "2021-11-09 08:41:01"
	},
	{
		"id" : 394280,
		"serial_reference" : "240115SH0C",
		"short_code" : "PTM",
		"date_created" : "2021-11-09 08:41:31",
		"last_updated" : "2021-11-09 08:41:31"
	},
	{
		"id" : 394288,
		"serial_reference" : "240115SH0D",
		"short_code" : "PTM",
		"date_created" : "2021-11-09 08:41:31",
		"last_updated" : "2021-11-09 08:41:31"
	},
	{
		"id" : 394328,
		"serial_reference" : "442514CA0BRP",
		"short_code" : "CTD",
		"date_created" : "2021-11-09 08:44:31",
		"last_updated" : "2021-11-09 08:44:31"
	},
	{
		"id" : 394336,
		"serial_reference" : "442504CA0BRP",
		"short_code" : "CTD",
		"date_created" : "2021-11-09 08:45:03",
		"last_updated" : "2021-11-09 08:45:03"
	},
	{
		"id" : 394344,
		"serial_reference" : "240116uA2C",
		"short_code" : "CTD",
		"date_created" : "2021-11-09 08:47:16",
		"last_updated" : "2021-11-09 08:47:16"
	},
	{
		"id" : 394352,
		"serial_reference" : "240116uA2C",
		"short_code" : "CTD",
		"date_created" : "2021-11-09 08:47:40",
		"last_updated" : "2021-11-09 08:47:40"
	},
	{
		"id" : 394360,
		"serial_reference" : "240116uA2C",
		"short_code" : "CTD",
		"date_created" : "2021-11-09 08:48:13",
		"last_updated" : "2021-11-09 08:48:13"
	},
	{
		"id" : 394368,
		"serial_reference" : "638465V000     ",
		"short_code" : "PTM",
		"date_created" : "2021-11-09 08:52:06",
		"last_updated" : "2021-11-09 08:52:06"
	},
	{
		"id" : 394392,
		"serial_reference" : "240126WK5A",
		"short_code" : "CTD",
		"date_created" : "2021-11-09 08:54:35",
		"last_updated" : "2021-11-09 08:54:35"
	},
	{
		"id" : 394400,
		"serial_reference" : "240126WK5A",
		"short_code" : "CTD",
		"date_created" : "2021-11-09 08:54:54",
		"last_updated" : "2021-11-09 08:54:54"
	},
	{
		"id" : 394408,
		"serial_reference" : "240126WK6A",
		"short_code" : "CTD",
		"date_created" : "2021-11-09 09:16:10",
		"last_updated" : "2021-11-09 09:16:10"
	},
	{
		"id" : 394416,
		"serial_reference" : "462062J00A     ",
		"short_code" : "PTM",
		"date_created" : "2021-11-09 09:22:42",
		"last_updated" : "2021-11-09 09:22:42"
	},
	{
		"id" : 395568,
		"serial_reference" : "240116uA2C",
		"short_code" : "CTD",
		"date_created" : "2021-11-09 09:29:45",
		"last_updated" : "2021-11-09 09:29:45"
	},
	{
		"id" : 395576,
		"serial_reference" : "240116uA2C",
		"short_code" : "CTD",
		"date_created" : "2021-11-09 09:30:06",
		"last_updated" : "2021-11-09 09:30:06"
	},
	{
		"id" : 395584,
		"serial_reference" : "240116uA2C",
		"short_code" : "CTD",
		"date_created" : "2021-11-09 09:30:48",
		"last_updated" : "2021-11-09 09:30:48"
	},
	{
		"id" : 395592,
		"serial_reference" : "240335SH0A",
		"short_code" : "PTM",
		"date_created" : "2021-11-09 09:43:25",
		"last_updated" : "2021-11-09 09:43:25"
	},
	{
		"id" : 395600,
		"serial_reference" : "240126WK6A",
		"short_code" : "CTD",
		"date_created" : "2021-11-09 09:50:42",
		"last_updated" : "2021-11-09 09:50:42"
	},
	{
		"id" : 395608,
		"serial_reference" : "240126WK6A",
		"short_code" : "CTD",
		"date_created" : "2021-11-09 09:50:56",
		"last_updated" : "2021-11-09 09:50:56"
	},
	{
		"id" : 395616,
		"serial_reference" : "240126WK5A",
		"short_code" : "CTD",
		"date_created" : "2021-11-09 09:51:33",
		"last_updated" : "2021-11-09 09:51:33"
	},
	{
		"id" : 395624,
		"serial_reference" : "240126WK6A",
		"short_code" : "CTD",
		"date_created" : "2021-11-09 09:51:59",
		"last_updated" : "2021-11-09 09:51:59"
	},
	{
		"id" : 395632,
		"serial_reference" : "682416PE0A",
		"short_code" : "RBTP",
		"date_created" : "2021-11-09 10:02:07",
		"last_updated" : "2021-11-09 10:02:07"
	},
	{
		"id" : 395640,
		"serial_reference" : "682416PA0A",
		"short_code" : "RBTP",
		"date_created" : "2021-11-09 10:04:28",
		"last_updated" : "2021-11-09 10:04:28"
	},
	{
		"id" : 395648,
		"serial_reference" : "682416PE0A",
		"short_code" : "RBTP",
		"date_created" : "2021-11-09 10:06:37",
		"last_updated" : "2021-11-09 10:06:37"
	},
	{
		"id" : 395656,
		"serial_reference" : "682416PE0A",
		"short_code" : "RBTP",
		"date_created" : "2021-11-09 10:06:38",
		"last_updated" : "2021-11-09 10:06:38"
	},
	{
		"id" : 395664,
		"serial_reference" : "682416PE1A",
		"short_code" : "RBTP",
		"date_created" : "2021-11-09 10:07:39",
		"last_updated" : "2021-11-09 10:07:39"
	},
	{
		"id" : 395672,
		"serial_reference" : "682416PE0A",
		"short_code" : "RBTP",
		"date_created" : "2021-11-09 10:09:02",
		"last_updated" : "2021-11-09 10:09:02"
	},
	{
		"id" : 395680,
		"serial_reference" : "682416PE1A",
		"short_code" : "RBTP",
		"date_created" : "2021-11-09 10:10:52",
		"last_updated" : "2021-11-09 10:10:52"
	},
	{
		"id" : 395688,
		"serial_reference" : "240126WK6A",
		"short_code" : "CTD",
		"date_created" : "2021-11-09 10:12:21",
		"last_updated" : "2021-11-09 10:12:21"
	},
	{
		"id" : 395696,
		"serial_reference" : "682416PA0A",
		"short_code" : "RBTP",
		"date_created" : "2021-11-09 10:12:44",
		"last_updated" : "2021-11-09 10:12:44"
	},
	{
		"id" : 395704,
		"serial_reference" : "682416PE0A",
		"short_code" : "RBTP",
		"date_created" : "2021-11-09 10:13:47",
		"last_updated" : "2021-11-09 10:13:47"
	},
	{
		"id" : 395712,
		"serial_reference" : "682416PE0A",
		"short_code" : "RBTP",
		"date_created" : "2021-11-09 10:15:19",
		"last_updated" : "2021-11-09 10:15:19"
	},
	{
		"id" : 395720,
		"serial_reference" : "240126WK6A",
		"short_code" : "CTD",
		"date_created" : "2021-11-09 10:18:50",
		"last_updated" : "2021-11-09 10:18:50"
	},
	{
		"id" : 395728,
		"serial_reference" : "969206PA0C",
		"short_code" : "RBTP",
		"date_created" : "2021-11-09 10:20:15",
		"last_updated" : "2021-11-09 10:20:15"
	},
	{
		"id" : 395736,
		"serial_reference" : "969206PA0C",
		"short_code" : "RBTP",
		"date_created" : "2021-11-09 10:20:15",
		"last_updated" : "2021-11-09 10:20:15"
	},
	{
		"id" : 395744,
		"serial_reference" : "240116UA2E",
		"short_code" : "CTD",
		"date_created" : "2021-11-09 10:29:39",
		"last_updated" : "2021-11-09 10:29:39"
	},
	{
		"id" : 395752,
		"serial_reference" : "969206PA0C",
		"short_code" : "RBTP",
		"date_created" : "2021-11-09 10:37:46",
		"last_updated" : "2021-11-09 10:37:46"
	},
	{
		"id" : 395760,
		"serial_reference" : "969206PA0C",
		"short_code" : "RBTP",
		"date_created" : "2021-11-09 10:37:47",
		"last_updated" : "2021-11-09 10:37:47"
	},
	{
		"id" : 395768,
		"serial_reference" : "969206PA0C",
		"short_code" : "RBTP",
		"date_created" : "2021-11-09 10:37:47",
		"last_updated" : "2021-11-09 10:37:47"
	},
	{
		"id" : 395784,
		"serial_reference" : "240106UD3D",
		"short_code" : "PTM",
		"date_created" : "2021-11-09 11:11:51",
		"last_updated" : "2021-11-09 11:11:51"
	},
	{
		"id" : 395800,
		"serial_reference" : "240126WK6A",
		"short_code" : "CTD",
		"date_created" : "2021-11-09 11:17:04",
		"last_updated" : "2021-11-09 11:17:04"
	},
	{
		"id" : 395808,
		"serial_reference" : "240106UD0E",
		"short_code" : "PTM",
		"date_created" : "2021-11-09 11:25:09",
		"last_updated" : "2021-11-09 11:25:09"
	},
	{
		"id" : 395848,
		"serial_reference" : "682416PA0A",
		"short_code" : "RBTP",
		"date_created" : "2021-11-09 11:35:33",
		"last_updated" : "2021-11-09 11:35:33"
	},
	{
		"id" : 395856,
		"serial_reference" : "240126WK6A",
		"short_code" : "CTD",
		"date_created" : "2021-11-09 11:36:59",
		"last_updated" : "2021-11-09 11:36:59"
	},
	{
		"id" : 395864,
		"serial_reference" : "969206PA0D",
		"short_code" : "RBTP",
		"date_created" : "2021-11-09 11:37:34",
		"last_updated" : "2021-11-09 11:37:34"
	},
	{
		"id" : 395872,
		"serial_reference" : "969206PA0D",
		"short_code" : "RBTP",
		"date_created" : "2021-11-09 11:37:34",
		"last_updated" : "2021-11-09 11:37:34"
	},
	{
		"id" : 395880,
		"serial_reference" : "969206PA0C",
		"short_code" : "RBTP",
		"date_created" : "2021-11-09 11:38:54",
		"last_updated" : "2021-11-09 11:38:54"
	},
	{
		"id" : 395888,
		"serial_reference" : "240606UA8A",
		"short_code" : "PTM",
		"date_created" : "2021-11-09 11:40:11",
		"last_updated" : "2021-11-09 11:40:11"
	},
	{
		"id" : 395912,
		"serial_reference" : "682416PE1A",
		"short_code" : "RBTP",
		"date_created" : "2021-11-09 11:46:34",
		"last_updated" : "2021-11-09 11:46:34"
	},
	{
		"id" : 395928,
		"serial_reference" : "682416PE0A",
		"short_code" : "RBTP",
		"date_created" : "2021-11-09 11:53:26",
		"last_updated" : "2021-11-09 11:53:26"
	},
	{
		"id" : 395944,
		"serial_reference" : "240106UD3D",
		"short_code" : "PTM",
		"date_created" : "2021-11-09 11:55:14",
		"last_updated" : "2021-11-09 11:55:14"
	},
	{
		"id" : 395960,
		"serial_reference" : "240116uA2B",
		"short_code" : "CTD",
		"date_created" : "2021-11-09 11:59:57",
		"last_updated" : "2021-11-09 11:59:57"
	},
	{
		"id" : 395968,
		"serial_reference" : "240116uA2B",
		"short_code" : "CTD",
		"date_created" : "2021-11-09 12:02:32",
		"last_updated" : "2021-11-09 12:02:32"
	},
	{
		"id" : 395976,
		"serial_reference" : "240116uA2B",
		"short_code" : "CTD",
		"date_created" : "2021-11-09 12:02:52",
		"last_updated" : "2021-11-09 12:02:52"
	},
	{
		"id" : 395984,
		"serial_reference" : "240116uA2B",
		"short_code" : "CTD",
		"date_created" : "2021-11-09 12:02:59",
		"last_updated" : "2021-11-09 12:02:59"
	},
	{
		"id" : 395992,
		"serial_reference" : "240116uA2B",
		"short_code" : "CTD",
		"date_created" : "2021-11-09 12:04:17",
		"last_updated" : "2021-11-09 12:04:17"
	},
	{
		"id" : 396000,
		"serial_reference" : "240125SN3C",
		"short_code" : "RBTP",
		"date_created" : "2021-11-09 12:05:45",
		"last_updated" : "2021-11-09 12:44:36"
	},
	{
		"id" : 396008,
		"serial_reference" : "240116uA2B",
		"short_code" : "RBTP",
		"date_created" : "2021-11-09 12:07:06",
		"last_updated" : "2021-11-09 12:44:29"
	},
	{
		"id" : 396016,
		"serial_reference" : "240116uA2B",
		"short_code" : "RBTP",
		"date_created" : "2021-11-09 12:07:06",
		"last_updated" : "2021-11-09 12:44:29"
	},
	{
		"id" : 396024,
		"serial_reference" : "240126WK6A",
		"short_code" : "CTD",
		"date_created" : "2021-11-09 12:07:22",
		"last_updated" : "2021-11-09 12:07:22"
	},
	{
		"id" : 396032,
		"serial_reference" : "240116uA2C",
		"short_code" : "RBTP",
		"date_created" : "2021-11-09 12:08:12",
		"last_updated" : "2021-11-09 12:44:34"
	},
	{
		"id" : 396040,
		"serial_reference" : "240116uA2C",
		"short_code" : "RBTP",
		"date_created" : "2021-11-09 12:08:12",
		"last_updated" : "2021-11-09 12:44:33"
	},
	{
		"id" : 396048,
		"serial_reference" : "240415SH0A",
		"short_code" : "RBTP",
		"date_created" : "2021-11-09 12:09:18",
		"last_updated" : "2021-11-09 12:09:18"
	},
	{
		"id" : 396056,
		"serial_reference" : "240335SH0A",
		"short_code" : "RBTP",
		"date_created" : "2021-11-09 12:09:19",
		"last_updated" : "2021-11-10 18:59:48"
	},
	{
		"id" : 396072,
		"serial_reference" : "240116uA2B",
		"short_code" : "RBTP",
		"date_created" : "2021-11-09 12:10:00",
		"last_updated" : "2021-11-09 12:44:29"
	},
	{
		"id" : 396080,
		"serial_reference" : "240116uA2B",
		"short_code" : "RBTP",
		"date_created" : "2021-11-09 12:10:56",
		"last_updated" : "2021-11-09 12:44:29"
	},
	{
		"id" : 396088,
		"serial_reference" : "240116uA2B",
		"short_code" : "RBTP",
		"date_created" : "2021-11-09 12:11:55",
		"last_updated" : "2021-11-09 12:44:29"
	},
	{
		"id" : 396096,
		"serial_reference" : "240116uA2B",
		"short_code" : "RBTP",
		"date_created" : "2021-11-09 12:11:55",
		"last_updated" : "2021-11-09 12:44:30"
	},
	{
		"id" : 396104,
		"serial_reference" : "240335SH0A",
		"short_code" : "RBTP",
		"date_created" : "2021-11-09 12:13:01",
		"last_updated" : "2021-11-11 20:01:59"
	},
	{
		"id" : 396112,
		"serial_reference" : "240335SH0A",
		"short_code" : "RBTP",
		"date_created" : "2021-11-09 12:13:01",
		"last_updated" : "2021-11-11 20:01:59"
	},
	{
		"id" : 396120,
		"serial_reference" : "240116uA2B",
		"short_code" : "RBTP",
		"date_created" : "2021-11-09 12:13:56",
		"last_updated" : "2021-11-09 12:44:30"
	},
	{
		"id" : 396128,
		"serial_reference" : "240116uA2B",
		"short_code" : "RBTP",
		"date_created" : "2021-11-09 12:13:56",
		"last_updated" : "2021-11-09 12:44:30"
	},
	{
		"id" : 396136,
		"serial_reference" : "240106UD3D",
		"short_code" : "RBTP",
		"date_created" : "2021-11-09 12:15:11",
		"last_updated" : "2021-11-09 12:44:25"
	},
	{
		"id" : 396144,
		"serial_reference" : "240106UD3D",
		"short_code" : "RBTP",
		"date_created" : "2021-11-09 12:15:11",
		"last_updated" : "2021-11-09 18:40:05"
	},
	{
		"id" : 396152,
		"serial_reference" : "240116uA2B",
		"short_code" : "RBTP",
		"date_created" : "2021-11-09 12:16:03",
		"last_updated" : "2021-11-09 12:44:30"
	},
	{
		"id" : 396160,
		"serial_reference" : "240116uA2B",
		"short_code" : "RBTP",
		"date_created" : "2021-11-09 12:16:03",
		"last_updated" : "2021-11-09 12:44:30"
	},
	{
		"id" : 396168,
		"serial_reference" : "240116uA2B",
		"short_code" : "RBTP",
		"date_created" : "2021-11-09 12:16:47",
		"last_updated" : "2021-11-09 12:44:30"
	},
	{
		"id" : 396176,
		"serial_reference" : "240116uA2B",
		"short_code" : "RBTP",
		"date_created" : "2021-11-09 12:16:48",
		"last_updated" : "2021-11-09 12:44:30"
	},
	{
		"id" : 396184,
		"serial_reference" : "240116uA2B",
		"short_code" : "PTM",
		"date_created" : "2021-11-09 12:17:06",
		"last_updated" : "2021-11-09 12:17:06"
	},
	{
		"id" : 396200,
		"serial_reference" : "240116uA2B",
		"short_code" : "RBTP",
		"date_created" : "2021-11-09 12:17:46",
		"last_updated" : "2021-11-09 12:44:31"
	},
	{
		"id" : 396208,
		"serial_reference" : "240116uA2B",
		"short_code" : "RBTP",
		"date_created" : "2021-11-09 12:17:46",
		"last_updated" : "2021-11-09 12:44:31"
	},
	{
		"id" : 396216,
		"serial_reference" : "240116uA2B",
		"short_code" : "RBTP",
		"date_created" : "2021-11-09 12:19:05",
		"last_updated" : "2021-11-09 12:44:31"
	},
	{
		"id" : 396224,
		"serial_reference" : "240116uA2B",
		"short_code" : "RBTP",
		"date_created" : "2021-11-09 12:19:05",
		"last_updated" : "2021-11-09 12:44:31"
	},
	{
		"id" : 396232,
		"serial_reference" : "240126WK6C",
		"short_code" : "RBTD",
		"date_created" : "2021-11-09 12:20:33",
		"last_updated" : "2021-11-09 12:44:42"
	},
	{
		"id" : 396240,
		"serial_reference" : "240106UC0A",
		"short_code" : "RBTD",
		"date_created" : "2021-11-09 12:21:08",
		"last_updated" : "2021-11-09 12:21:08"
	},
	{
		"id" : 396256,
		"serial_reference" : "682416PE0A",
		"short_code" : "PTS",
		"date_created" : "2021-11-09 12:21:48",
		"last_updated" : "2021-11-09 12:21:48"
	},
	{
		"id" : 396264,
		"serial_reference" : "682416PE0A",
		"short_code" : "PTS",
		"date_created" : "2021-11-09 12:21:48",
		"last_updated" : "2021-11-09 12:21:48"
	},
	{
		"id" : 396272,
		"serial_reference" : "240126WK6A",
		"short_code" : "RBTD",
		"date_created" : "2021-11-09 12:22:29",
		"last_updated" : "2021-11-09 12:44:40"
	},
	{
		"id" : 396280,
		"serial_reference" : "240116UA2E",
		"short_code" : "RBTD",
		"date_created" : "2021-11-09 12:23:18",
		"last_updated" : "2021-11-09 12:44:35"
	},
	{
		"id" : 396288,
		"serial_reference" : "240116UA2D",
		"short_code" : "RBTD",
		"date_created" : "2021-11-09 12:23:51",
		"last_updated" : "2021-11-09 12:23:51"
	},
	{
		"id" : 396296,
		"serial_reference" : "240116UA2E",
		"short_code" : "RBTD",
		"date_created" : "2021-11-09 12:24:26",
		"last_updated" : "2021-11-09 12:44:35"
	},
	{
		"id" : 396304,
		"serial_reference" : "240116UA2E",
		"short_code" : "RBTD",
		"date_created" : "2021-11-09 12:25:00",
		"last_updated" : "2021-11-09 12:44:35"
	},
	{
		"id" : 396312,
		"serial_reference" : "682416PE1A",
		"short_code" : "PTS",
		"date_created" : "2021-11-09 12:32:03",
		"last_updated" : "2021-11-09 12:32:03"
	},
	{
		"id" : 396320,
		"serial_reference" : "240125SH9C",
		"short_code" : "CTD",
		"date_created" : "2021-11-09 12:35:32",
		"last_updated" : "2021-11-09 12:35:32"
	},
	{
		"id" : 396328,
		"serial_reference" : "295J14NR0A",
		"short_code" : "RBTP",
		"date_created" : "2021-11-09 12:38:57",
		"last_updated" : "2021-11-09 12:38:57"
	},
	{
		"id" : 396336,
		"serial_reference" : "295J14NR0A",
		"short_code" : "RBTP",
		"date_created" : "2021-11-09 12:38:57",
		"last_updated" : "2021-11-09 12:38:57"
	},
	{
		"id" : 396344,
		"serial_reference" : "295J14NR0A",
		"short_code" : "RBTP",
		"date_created" : "2021-11-09 12:38:57",
		"last_updated" : "2021-11-09 12:38:57"
	},
	{
		"id" : 396352,
		"serial_reference" : "682416PE0A",
		"short_code" : "PTS",
		"date_created" : "2021-11-09 12:42:32",
		"last_updated" : "2021-11-09 12:42:32"
	},
	{
		"id" : 396360,
		"serial_reference" : "682416PE0A",
		"short_code" : "PTS",
		"date_created" : "2021-11-09 12:47:47",
		"last_updated" : "2021-11-09 12:47:47"
	},
	{
		"id" : 396368,
		"serial_reference" : "240116uA2B",
		"short_code" : "PTS",
		"date_created" : "2021-11-09 12:49:02",
		"last_updated" : "2021-11-09 12:49:02"
	},
	{
		"id" : 396376,
		"serial_reference" : "240116uA2B",
		"short_code" : "PTS",
		"date_created" : "2021-11-09 12:49:02",
		"last_updated" : "2021-11-09 12:49:02"
	},
	{
		"id" : 396384,
		"serial_reference" : "240116uA2B",
		"short_code" : "PTS",
		"date_created" : "2021-11-09 12:50:35",
		"last_updated" : "2021-11-09 12:50:35"
	},
	{
		"id" : 396392,
		"serial_reference" : "240125SH9C",
		"short_code" : "CTD",
		"date_created" : "2021-11-09 12:50:42",
		"last_updated" : "2021-11-09 12:50:42"
	},
	{
		"id" : 396400,
		"serial_reference" : "682416PA0A",
		"short_code" : "PTS",
		"date_created" : "2021-11-09 12:56:39",
		"last_updated" : "2021-11-09 12:56:39"
	},
	{
		"id" : 396408,
		"serial_reference" : "240125SH9C",
		"short_code" : "CTD",
		"date_created" : "2021-11-09 12:58:03",
		"last_updated" : "2021-11-09 12:58:03"
	},
	{
		"id" : 396416,
		"serial_reference" : "240116uA2C",
		"short_code" : "PTS",
		"date_created" : "2021-11-09 12:59:45",
		"last_updated" : "2021-11-09 12:59:45"
	},
	{
		"id" : 396424,
		"serial_reference" : "240116uA2C",
		"short_code" : "PTS",
		"date_created" : "2021-11-09 12:59:45",
		"last_updated" : "2021-11-09 12:59:45"
	},
	{
		"id" : 396448,
		"serial_reference" : "240335SH0A",
		"short_code" : "PTS",
		"date_created" : "2021-11-09 13:01:38",
		"last_updated" : "2021-11-09 13:01:38"
	},
	{
		"id" : 396456,
		"serial_reference" : "240415SH0A",
		"short_code" : "PTS",
		"date_created" : "2021-11-09 13:01:43",
		"last_updated" : "2021-11-09 13:01:43"
	},
	{
		"id" : 396472,
		"serial_reference" : "240116uA2B",
		"short_code" : "PTS",
		"date_created" : "2021-11-09 13:07:35",
		"last_updated" : "2021-11-09 13:07:35"
	},
	{
		"id" : 396480,
		"serial_reference" : "240116uA2B",
		"short_code" : "PTS",
		"date_created" : "2021-11-09 13:07:35",
		"last_updated" : "2021-11-09 13:07:35"
	},
	{
		"id" : 396488,
		"serial_reference" : "682416PA0A",
		"short_code" : "PTS",
		"date_created" : "2021-11-09 13:08:46",
		"last_updated" : "2021-11-09 13:08:46"
	},
	{
		"id" : 396504,
		"serial_reference" : "240106UD3D",
		"short_code" : "PTS",
		"date_created" : "2021-11-09 13:09:28",
		"last_updated" : "2021-11-09 13:09:28"
	},
	{
		"id" : 396528,
		"serial_reference" : "240116uA2B",
		"short_code" : "PTS",
		"date_created" : "2021-11-09 13:14:42",
		"last_updated" : "2021-11-09 13:14:42"
	},
	{
		"id" : 396536,
		"serial_reference" : "240116uA2B",
		"short_code" : "PTS",
		"date_created" : "2021-11-09 13:14:42",
		"last_updated" : "2021-11-09 13:14:42"
	},
	{
		"id" : 396544,
		"serial_reference" : "682416PE1A",
		"short_code" : "PTS",
		"date_created" : "2021-11-09 13:15:19",
		"last_updated" : "2021-11-09 13:15:19"
	},
	{
		"id" : 396552,
		"serial_reference" : "240606UA1A",
		"short_code" : "PTS",
		"date_created" : "2021-11-09 13:16:18",
		"last_updated" : "2021-11-09 13:16:18"
	},
	{
		"id" : 396560,
		"serial_reference" : "240335SH0A",
		"short_code" : "PTS",
		"date_created" : "2021-11-09 13:16:40",
		"last_updated" : "2021-11-09 13:16:40"
	},
	{
		"id" : 396568,
		"serial_reference" : "240125SN3C",
		"short_code" : "PTS",
		"date_created" : "2021-11-09 13:22:09",
		"last_updated" : "2021-11-09 13:22:09"
	},
	{
		"id" : 396576,
		"serial_reference" : "682416PE0A",
		"short_code" : "PTS",
		"date_created" : "2021-11-09 13:24:46",
		"last_updated" : "2021-11-09 13:24:46"
	},
	{
		"id" : 396584,
		"serial_reference" : "682416PE0A",
		"short_code" : "PTS",
		"date_created" : "2021-11-09 13:24:46",
		"last_updated" : "2021-11-09 13:24:46"
	},
	{
		"id" : 396592,
		"serial_reference" : "240116uA2B",
		"short_code" : "PTS",
		"date_created" : "2021-11-09 13:26:58",
		"last_updated" : "2021-11-09 13:26:58"
	},
	{
		"id" : 396600,
		"serial_reference" : "240116uA2B",
		"short_code" : "PTS",
		"date_created" : "2021-11-09 13:26:58",
		"last_updated" : "2021-11-09 13:26:58"
	},
	{
		"id" : 396608,
		"serial_reference" : "240116uA2B",
		"short_code" : "CTD",
		"date_created" : "2021-11-09 13:40:16",
		"last_updated" : "2021-11-09 13:40:16"
	},
	{
		"id" : 396616,
		"serial_reference" : "240126WK5A",
		"short_code" : "CTD",
		"date_created" : "2021-11-09 13:58:20",
		"last_updated" : "2021-11-09 13:58:20"
	},
	{
		"id" : 396624,
		"serial_reference" : "240126WK5A",
		"short_code" : "CTD",
		"date_created" : "2021-11-09 13:59:08",
		"last_updated" : "2021-11-09 13:59:08"
	},
	{
		"id" : 396640,
		"serial_reference" : "240116uA2B",
		"short_code" : "PTS",
		"date_created" : "2021-11-09 14:09:34",
		"last_updated" : "2021-11-09 14:09:34"
	},
	{
		"id" : 396648,
		"serial_reference" : "240116uA2B",
		"short_code" : "PTS",
		"date_created" : "2021-11-09 14:09:34",
		"last_updated" : "2021-11-09 14:09:34"
	},
	{
		"id" : 396656,
		"serial_reference" : "240116uA2B",
		"short_code" : "PTS",
		"date_created" : "2021-11-09 14:12:36",
		"last_updated" : "2021-11-09 14:12:36"
	},
	{
		"id" : 396664,
		"serial_reference" : "240116uA2B",
		"short_code" : "PTS",
		"date_created" : "2021-11-09 14:12:37",
		"last_updated" : "2021-11-09 14:12:37"
	},
	{
		"id" : 396680,
		"serial_reference" : "240116uA2B",
		"short_code" : "PTS",
		"date_created" : "2021-11-09 14:17:09",
		"last_updated" : "2021-11-09 14:17:09"
	},
	{
		"id" : 396688,
		"serial_reference" : "240116uA2B",
		"short_code" : "PTS",
		"date_created" : "2021-11-09 14:17:09",
		"last_updated" : "2021-11-09 14:17:09"
	},
	{
		"id" : 396704,
		"serial_reference" : "240116uA2B",
		"short_code" : "PTS",
		"date_created" : "2021-11-09 14:19:11",
		"last_updated" : "2021-11-09 14:19:11"
	},
	{
		"id" : 396712,
		"serial_reference" : "240116uA2B",
		"short_code" : "PTS",
		"date_created" : "2021-11-09 14:19:12",
		"last_updated" : "2021-11-09 14:19:12"
	},
	{
		"id" : 396736,
		"serial_reference" : "295B84NR0A",
		"short_code" : "PTM",
		"date_created" : "2021-11-09 14:28:05",
		"last_updated" : "2021-11-09 14:28:05"
	},
	{
		"id" : 396744,
		"serial_reference" : "295B84NR0A",
		"short_code" : "PTM",
		"date_created" : "2021-11-09 14:28:05",
		"last_updated" : "2021-11-09 14:28:05"
	},
	{
		"id" : 396752,
		"serial_reference" : "295J14NR0A",
		"short_code" : "PTM",
		"date_created" : "2021-11-09 14:28:05",
		"last_updated" : "2021-11-09 14:28:05"
	},
	{
		"id" : 396760,
		"serial_reference" : "295J14NR0A",
		"short_code" : "PTM",
		"date_created" : "2021-11-09 14:28:05",
		"last_updated" : "2021-11-09 14:28:05"
	},
	{
		"id" : 396768,
		"serial_reference" : "295J14NR0A",
		"short_code" : "PTM",
		"date_created" : "2021-11-09 14:28:05",
		"last_updated" : "2021-11-09 14:28:05"
	},
	{
		"id" : 396776,
		"serial_reference" : "295J14NR0A",
		"short_code" : "PTM",
		"date_created" : "2021-11-09 14:28:05",
		"last_updated" : "2021-11-09 14:28:05"
	},
	{
		"id" : 396784,
		"serial_reference" : "295J14NR0A",
		"short_code" : "PTM",
		"date_created" : "2021-11-09 14:28:05",
		"last_updated" : "2021-11-09 14:28:05"
	},
	{
		"id" : 396792,
		"serial_reference" : "295L14NR0A",
		"short_code" : "PTM",
		"date_created" : "2021-11-09 14:28:05",
		"last_updated" : "2021-11-09 14:28:05"
	},
	{
		"id" : 396800,
		"serial_reference" : "295L14NR0A",
		"short_code" : "PTM",
		"date_created" : "2021-11-09 14:28:05",
		"last_updated" : "2021-11-09 14:28:05"
	},
	{
		"id" : 396880,
		"serial_reference" : "240116uA2B",
		"short_code" : "CTD",
		"date_created" : "2021-11-09 14:30:12",
		"last_updated" : "2021-11-09 14:30:12"
	},
	{
		"id" : 396888,
		"serial_reference" : "240116uA2B",
		"short_code" : "CTD",
		"date_created" : "2021-11-09 14:30:34",
		"last_updated" : "2021-11-09 14:30:34"
	},
	{
		"id" : 396904,
		"serial_reference" : "969206PA0C",
		"short_code" : "PTS",
		"date_created" : "2021-11-09 14:31:45",
		"last_updated" : "2021-11-09 14:31:45"
	},
	{
		"id" : 396912,
		"serial_reference" : "969206PA0C",
		"short_code" : "PTS",
		"date_created" : "2021-11-09 14:31:46",
		"last_updated" : "2021-11-09 14:31:46"
	},
	{
		"id" : 396920,
		"serial_reference" : "969206PA0C",
		"short_code" : "PTS",
		"date_created" : "2021-11-09 14:31:46",
		"last_updated" : "2021-11-09 14:31:46"
	},
	{
		"id" : 396928,
		"serial_reference" : "233000290R",
		"short_code" : "CTS",
		"date_created" : "2021-11-09 14:32:08",
		"last_updated" : "2021-11-09 14:32:08"
	},
	{
		"id" : 396944,
		"serial_reference" : "969206PA0C",
		"short_code" : "PTS",
		"date_created" : "2021-11-09 14:36:36",
		"last_updated" : "2021-11-09 14:36:36"
	},
	{
		"id" : 396952,
		"serial_reference" : "969206PA0C",
		"short_code" : "PTS",
		"date_created" : "2021-11-09 14:36:36",
		"last_updated" : "2021-11-09 14:36:36"
	},
	{
		"id" : 396960,
		"serial_reference" : "240116uA2B",
		"short_code" : "CTD",
		"date_created" : "2021-11-09 14:38:21",
		"last_updated" : "2021-11-09 14:38:21"
	},
	{
		"id" : 396968,
		"serial_reference" : "240116uA2B",
		"short_code" : "CTD",
		"date_created" : "2021-11-09 14:38:46",
		"last_updated" : "2021-11-09 14:38:46"
	},
	{
		"id" : 396976,
		"serial_reference" : "682416PE0A",
		"short_code" : "PTS",
		"date_created" : "2021-11-09 14:43:02",
		"last_updated" : "2021-11-09 14:43:02"
	},
	{
		"id" : 396984,
		"serial_reference" : "240116uA2B",
		"short_code" : "CTD",
		"date_created" : "2021-11-09 14:43:21",
		"last_updated" : "2021-11-09 14:43:21"
	},
	{
		"id" : 396992,
		"serial_reference" : "240116uA2B",
		"short_code" : "CTD",
		"date_created" : "2021-11-09 14:43:45",
		"last_updated" : "2021-11-09 14:43:45"
	},
	{
		"id" : 397000,
		"serial_reference" : "969206PA0C",
		"short_code" : "PTS",
		"date_created" : "2021-11-09 14:48:03",
		"last_updated" : "2021-11-09 14:48:03"
	},
	{
		"id" : 397016,
		"serial_reference" : "682416PE0A",
		"short_code" : "PTS",
		"date_created" : "2021-11-09 14:55:56",
		"last_updated" : "2021-11-09 14:55:56"
	},
	{
		"id" : 397024,
		"serial_reference" : "969206PA0D",
		"short_code" : "PTS",
		"date_created" : "2021-11-09 15:00:35",
		"last_updated" : "2021-11-09 15:00:35"
	},
	{
		"id" : 397032,
		"serial_reference" : "969206PA0D",
		"short_code" : "PTS",
		"date_created" : "2021-11-09 15:00:35",
		"last_updated" : "2021-11-09 15:00:35"
	},
	{
		"id" : 397040,
		"serial_reference" : "682416PA0A",
		"short_code" : "PTS",
		"date_created" : "2021-11-09 15:21:11",
		"last_updated" : "2021-11-09 15:21:11"
	},
	{
		"id" : 397056,
		"serial_reference" : "682416PE1A",
		"short_code" : "PTS",
		"date_created" : "2021-11-09 15:27:10",
		"last_updated" : "2021-11-09 15:27:10"
	},
	{
		"id" : 397064,
		"serial_reference" : "682416PE1A",
		"short_code" : "PTS",
		"date_created" : "2021-11-09 15:27:10",
		"last_updated" : "2021-11-09 15:27:10"
	},
	{
		"id" : 397128,
		"serial_reference" : "240116UA2D",
		"short_code" : "CTD",
		"date_created" : "2021-11-09 15:50:27",
		"last_updated" : "2021-11-09 15:50:27"
	},
	{
		"id" : 397136,
		"serial_reference" : "240116UA2E",
		"short_code" : "CTD",
		"date_created" : "2021-11-09 15:50:53",
		"last_updated" : "2021-11-09 15:50:53"
	},
	{
		"id" : 397144,
		"serial_reference" : "240116UA2E",
		"short_code" : "CTD",
		"date_created" : "2021-11-09 15:51:24",
		"last_updated" : "2021-11-09 15:51:24"
	},
	{
		"id" : 397184,
		"serial_reference" : "240116uA2C",
		"short_code" : "CTD",
		"date_created" : "2021-11-09 16:01:04",
		"last_updated" : "2021-11-09 16:01:04"
	},
	{
		"id" : 397216,
		"serial_reference" : "240116uA2C",
		"short_code" : "CTD",
		"date_created" : "2021-11-09 16:01:50",
		"last_updated" : "2021-11-09 16:01:50"
	},
	{
		"id" : 397248,
		"serial_reference" : "240116uA2C",
		"short_code" : "CTD",
		"date_created" : "2021-11-09 16:05:17",
		"last_updated" : "2021-11-09 16:05:17"
	},
	{
		"id" : 397280,
		"serial_reference" : "240116uA2C",
		"short_code" : "CTD",
		"date_created" : "2021-11-09 16:07:49",
		"last_updated" : "2021-11-09 16:07:49"
	},
	{
		"id" : 397288,
		"serial_reference" : "240116uA2C",
		"short_code" : "CTD",
		"date_created" : "2021-11-09 16:08:13",
		"last_updated" : "2021-11-09 16:08:13"
	},
	{
		"id" : 397408,
		"serial_reference" : "240106ub9d",
		"short_code" : "PTM",
		"date_created" : "2021-11-09 16:51:49",
		"last_updated" : "2021-11-09 16:51:49"
	},
	{
		"id" : 397416,
		"serial_reference" : "240106ub9d",
		"short_code" : "PTM",
		"date_created" : "2021-11-09 16:51:49",
		"last_updated" : "2021-11-09 16:51:49"
	},
	{
		"id" : 397480,
		"serial_reference" : "295L14NR0A",
		"short_code" : "RBTP",
		"date_created" : "2021-11-09 17:02:32",
		"last_updated" : "2021-11-09 17:02:32"
	},
	{
		"id" : 397512,
		"serial_reference" : "295L14NR0A",
		"short_code" : "RBTP",
		"date_created" : "2021-11-09 17:04:32",
		"last_updated" : "2021-11-09 17:04:32"
	},
	{
		"id" : 397520,
		"serial_reference" : "295L14NR0A",
		"short_code" : "RBTP",
		"date_created" : "2021-11-09 17:05:23",
		"last_updated" : "2021-11-09 17:05:23"
	},
	{
		"id" : 397528,
		"serial_reference" : "295L14NR0A",
		"short_code" : "RBTP",
		"date_created" : "2021-11-09 17:07:32",
		"last_updated" : "2021-11-09 17:07:32"
	},
	{
		"id" : 397544,
		"serial_reference" : "295L14NR0A",
		"short_code" : "RBTP",
		"date_created" : "2021-11-09 17:08:42",
		"last_updated" : "2021-11-09 17:08:42"
	},
	{
		"id" : 397552,
		"serial_reference" : "295L14NR0A",
		"short_code" : "RBTP",
		"date_created" : "2021-11-09 17:09:27",
		"last_updated" : "2021-11-09 17:09:27"
	},
	{
		"id" : 397560,
		"serial_reference" : "295L14NR0A",
		"short_code" : "RBTP",
		"date_created" : "2021-11-09 17:10:10",
		"last_updated" : "2021-11-09 17:10:10"
	},
	{
		"id" : 397568,
		"serial_reference" : "295L14NR0A",
		"short_code" : "RBTP",
		"date_created" : "2021-11-09 17:11:02",
		"last_updated" : "2021-11-09 17:11:02"
	},
	{
		"id" : 397576,
		"serial_reference" : "295L14NR0A",
		"short_code" : "RBTP",
		"date_created" : "2021-11-09 17:11:40",
		"last_updated" : "2021-11-09 17:11:40"
	},
	{
		"id" : 397600,
		"serial_reference" : "243506RA0B",
		"short_code" : "RBTP",
		"date_created" : "2021-11-09 17:25:04",
		"last_updated" : "2021-11-09 17:25:04"
	},
	{
		"id" : 397608,
		"serial_reference" : "243506RA0B",
		"short_code" : "RBTP",
		"date_created" : "2021-11-09 17:25:04",
		"last_updated" : "2021-11-09 17:25:04"
	},
	{
		"id" : 397616,
		"serial_reference" : "243506RA0B",
		"short_code" : "RBTP",
		"date_created" : "2021-11-09 17:25:04",
		"last_updated" : "2021-11-09 17:25:04"
	},
	{
		"id" : 397632,
		"serial_reference" : "240106UD3D",
		"short_code" : "PTM",
		"date_created" : "2021-11-09 17:29:32",
		"last_updated" : "2021-11-09 17:29:32"
	},
	{
		"id" : 397648,
		"serial_reference" : "243506RA0B",
		"short_code" : "RBTP",
		"date_created" : "2021-11-09 17:37:20",
		"last_updated" : "2021-11-09 17:37:20"
	},
	{
		"id" : 397656,
		"serial_reference" : "243506RA0B",
		"short_code" : "RBTP",
		"date_created" : "2021-11-09 17:37:20",
		"last_updated" : "2021-11-09 17:37:20"
	},
	{
		"id" : 397664,
		"serial_reference" : "243506RA0B",
		"short_code" : "RBTP",
		"date_created" : "2021-11-09 17:37:20",
		"last_updated" : "2021-11-09 17:37:20"
	},
	{
		"id" : 397688,
		"serial_reference" : "240106UD3D",
		"short_code" : "PTM",
		"date_created" : "2021-11-09 17:53:38",
		"last_updated" : "2021-11-09 17:53:38"
	},
	{
		"id" : 397696,
		"serial_reference" : "240106UD3D",
		"short_code" : "PTM",
		"date_created" : "2021-11-09 17:53:39",
		"last_updated" : "2021-11-09 17:53:39"
	},
	{
		"id" : 397736,
		"serial_reference" : "240126WK6A",
		"short_code" : "CTS",
		"date_created" : "2021-11-09 18:11:00",
		"last_updated" : "2021-11-09 18:11:00"
	},
	{
		"id" : 397744,
		"serial_reference" : "240606UJ1a",
		"short_code" : "PTM",
		"date_created" : "2021-11-09 18:13:49",
		"last_updated" : "2021-11-09 18:13:49"
	},
	{
		"id" : 397760,
		"serial_reference" : "240126WK8A",
		"short_code" : "CTS",
		"date_created" : "2021-11-09 18:22:11",
		"last_updated" : "2021-11-09 18:22:11"
	},
	{
		"id" : 397768,
		"serial_reference" : "240126WK6A",
		"short_code" : "CTS",
		"date_created" : "2021-11-09 18:26:19",
		"last_updated" : "2021-11-09 18:26:19"
	},
	{
		"id" : 397776,
		"serial_reference" : "240126WK6D",
		"short_code" : "PTM",
		"date_created" : "2021-11-09 18:28:10",
		"last_updated" : "2021-11-09 18:28:10"
	},
	{
		"id" : 397824,
		"serial_reference" : "240106UD3C",
		"short_code" : "CTS",
		"date_created" : "2021-11-09 18:34:48",
		"last_updated" : "2021-11-09 18:34:48"
	},
	{
		"id" : 397848,
		"serial_reference" : "240126WK8A",
		"short_code" : "CTS",
		"date_created" : "2021-11-09 18:47:10",
		"last_updated" : "2021-11-09 18:47:10"
	},
	{
		"id" : 397880,
		"serial_reference" : "240106ub9d",
		"short_code" : "PTM",
		"date_created" : "2021-11-09 19:18:35",
		"last_updated" : "2021-11-09 19:18:35"
	},
	{
		"id" : 397888,
		"serial_reference" : "240106ub9d",
		"short_code" : "PTM",
		"date_created" : "2021-11-09 19:18:35",
		"last_updated" : "2021-11-09 19:18:35"
	},
	{
		"id" : 397896,
		"serial_reference" : "240115SH0C",
		"short_code" : "PTM",
		"date_created" : "2021-11-09 19:18:35",
		"last_updated" : "2021-11-09 19:18:35"
	},
	{
		"id" : 397904,
		"serial_reference" : "240115SH0D",
		"short_code" : "PTM",
		"date_created" : "2021-11-09 19:18:35",
		"last_updated" : "2021-11-09 19:18:35"
	},
	{
		"id" : 398008,
		"serial_reference" : "240186UA0A",
		"short_code" : "PTM",
		"date_created" : "2021-11-09 21:03:02",
		"last_updated" : "2021-11-09 21:03:02"
	},
	{
		"id" : 398064,
		"serial_reference" : "240106UD3D",
		"short_code" : "PTM",
		"date_created" : "2021-11-09 22:17:50",
		"last_updated" : "2021-11-09 22:17:50"
	},
	{
		"id" : 398232,
		"serial_reference" : "295L14NR0A",
		"short_code" : "PTS",
		"date_created" : "2021-11-10 00:07:19",
		"last_updated" : "2021-11-10 00:07:19"
	},
	{
		"id" : 398240,
		"serial_reference" : "295L14NR0A",
		"short_code" : "PTS",
		"date_created" : "2021-11-10 00:09:44",
		"last_updated" : "2021-11-10 00:09:44"
	},
	{
		"id" : 398248,
		"serial_reference" : "295L14NR0A",
		"short_code" : "PTS",
		"date_created" : "2021-11-10 00:10:31",
		"last_updated" : "2021-11-10 00:10:31"
	},
	{
		"id" : 398256,
		"serial_reference" : "295L14NR0A",
		"short_code" : "PTS",
		"date_created" : "2021-11-10 00:10:43",
		"last_updated" : "2021-11-10 00:10:43"
	},
	{
		"id" : 398264,
		"serial_reference" : "295L14NR0A",
		"short_code" : "PTS",
		"date_created" : "2021-11-10 00:14:16",
		"last_updated" : "2021-11-10 00:14:16"
	},
	{
		"id" : 398272,
		"serial_reference" : "295L14NR0A",
		"short_code" : "PTS",
		"date_created" : "2021-11-10 00:14:30",
		"last_updated" : "2021-11-10 00:14:30"
	},
	{
		"id" : 398280,
		"serial_reference" : "295L14NR0A",
		"short_code" : "PTS",
		"date_created" : "2021-11-10 00:18:08",
		"last_updated" : "2021-11-10 00:18:08"
	},
	{
		"id" : 398288,
		"serial_reference" : "295L14NR0A",
		"short_code" : "PTS",
		"date_created" : "2021-11-10 00:18:19",
		"last_updated" : "2021-11-10 00:18:19"
	},
	{
		"id" : 398320,
		"serial_reference" : "233000290R",
		"short_code" : "PTM",
		"date_created" : "2021-11-10 07:23:04",
		"last_updated" : "2021-11-10 07:23:04"
	},
	{
		"id" : 398352,
		"serial_reference" : "240126WK6A",
		"short_code" : "PTM",
		"date_created" : "2021-11-10 08:05:15",
		"last_updated" : "2021-11-10 08:05:15"
	},
	{
		"id" : 398360,
		"serial_reference" : "240125SJ4B",
		"short_code" : "PTM",
		"date_created" : "2021-11-10 08:05:15",
		"last_updated" : "2021-11-10 08:05:15"
	},
	{
		"id" : 398440,
		"serial_reference" : "240335SH0A",
		"short_code" : "PTM",
		"date_created" : "2021-11-10 08:25:28",
		"last_updated" : "2021-11-10 08:25:28"
	},
	{
		"id" : 398448,
		"serial_reference" : "240115SH0D",
		"short_code" : "PTM",
		"date_created" : "2021-11-10 08:25:28",
		"last_updated" : "2021-11-10 08:25:28"
	},
	{
		"id" : 398536,
		"serial_reference" : "240126WK5A",
		"short_code" : "CTD",
		"date_created" : "2021-11-10 08:37:46",
		"last_updated" : "2021-11-10 08:37:46"
	},
	{
		"id" : 398576,
		"serial_reference" : "240126WK6A",
		"short_code" : "CTD",
		"date_created" : "2021-11-10 08:53:52",
		"last_updated" : "2021-11-10 08:53:52"
	},
	{
		"id" : 398608,
		"serial_reference" : "240116uA2B",
		"short_code" : "CTD",
		"date_created" : "2021-11-10 08:57:13",
		"last_updated" : "2021-11-10 08:57:13"
	},
	{
		"id" : 398616,
		"serial_reference" : "240116uA2B",
		"short_code" : "CTD",
		"date_created" : "2021-11-10 08:57:42",
		"last_updated" : "2021-11-10 08:57:42"
	},
	{
		"id" : 398624,
		"serial_reference" : "240126WK6A",
		"short_code" : "CTD",
		"date_created" : "2021-11-10 09:01:53",
		"last_updated" : "2021-11-10 09:01:53"
	},
	{
		"id" : 398632,
		"serial_reference" : "240116uA2B",
		"short_code" : "CTD",
		"date_created" : "2021-11-10 09:03:50",
		"last_updated" : "2021-11-10 09:03:50"
	},
	{
		"id" : 398656,
		"serial_reference" : "240116uA2B",
		"short_code" : "CTD",
		"date_created" : "2021-11-10 09:07:07",
		"last_updated" : "2021-11-10 09:07:07"
	},
	{
		"id" : 398664,
		"serial_reference" : "240116uA2B",
		"short_code" : "CTD",
		"date_created" : "2021-11-10 09:07:22",
		"last_updated" : "2021-11-10 09:07:22"
	},
	{
		"id" : 398672,
		"serial_reference" : "240106UD4B",
		"short_code" : "CTD",
		"date_created" : "2021-11-10 09:12:14",
		"last_updated" : "2021-11-10 09:12:14"
	},
	{
		"id" : 398688,
		"serial_reference" : "240606UJ1a",
		"short_code" : "PTM",
		"date_created" : "2021-11-10 09:15:17",
		"last_updated" : "2021-11-10 09:15:17"
	},
	{
		"id" : 398752,
		"serial_reference" : "240116UA2E",
		"short_code" : "CTD",
		"date_created" : "2021-11-10 10:25:46",
		"last_updated" : "2021-11-10 10:25:46"
	},
	{
		"id" : 398760,
		"serial_reference" : "240606UJ1a",
		"short_code" : "PTM",
		"date_created" : "2021-11-10 11:03:31",
		"last_updated" : "2021-11-10 11:03:31"
	},
	{
		"id" : 398792,
		"serial_reference" : "682416PA0A",
		"short_code" : "RBTP",
		"date_created" : "2021-11-10 11:34:14",
		"last_updated" : "2021-11-10 11:34:14"
	},
	{
		"id" : 398800,
		"serial_reference" : "682416PA0A",
		"short_code" : "RBTP",
		"date_created" : "2021-11-10 11:34:15",
		"last_updated" : "2021-11-10 11:34:15"
	},
	{
		"id" : 398808,
		"serial_reference" : "969206PA0A",
		"short_code" : "RBTP",
		"date_created" : "2021-11-10 11:35:58",
		"last_updated" : "2021-11-10 11:35:58"
	},
	{
		"id" : 398816,
		"serial_reference" : "969206PA0A",
		"short_code" : "RBTP",
		"date_created" : "2021-11-10 11:35:58",
		"last_updated" : "2021-11-10 11:35:58"
	},
	{
		"id" : 398824,
		"serial_reference" : "969206PA0A",
		"short_code" : "RBTP",
		"date_created" : "2021-11-10 11:37:27",
		"last_updated" : "2021-11-10 11:37:27"
	},
	{
		"id" : 398832,
		"serial_reference" : "969206PA0A",
		"short_code" : "RBTP",
		"date_created" : "2021-11-10 11:37:27",
		"last_updated" : "2021-11-10 11:37:27"
	},
	{
		"id" : 398840,
		"serial_reference" : "969206PA0A",
		"short_code" : "RBTP",
		"date_created" : "2021-11-10 11:37:27",
		"last_updated" : "2021-11-10 11:37:27"
	},
	{
		"id" : 398848,
		"serial_reference" : "969206PA0A",
		"short_code" : "RBTP",
		"date_created" : "2021-11-10 11:39:01",
		"last_updated" : "2021-11-10 11:39:01"
	},
	{
		"id" : 398856,
		"serial_reference" : "969206PA0A",
		"short_code" : "RBTP",
		"date_created" : "2021-11-10 11:39:01",
		"last_updated" : "2021-11-10 11:39:01"
	},
	{
		"id" : 398864,
		"serial_reference" : "682416PA0A",
		"short_code" : "RBTP",
		"date_created" : "2021-11-10 11:39:29",
		"last_updated" : "2021-11-10 11:39:29"
	},
	{
		"id" : 398872,
		"serial_reference" : "969206PA0A",
		"short_code" : "RBTP",
		"date_created" : "2021-11-10 11:41:06",
		"last_updated" : "2021-11-10 11:41:06"
	},
	{
		"id" : 398880,
		"serial_reference" : "969206PA0A",
		"short_code" : "RBTP",
		"date_created" : "2021-11-10 11:41:06",
		"last_updated" : "2021-11-10 11:41:06"
	},
	{
		"id" : 398888,
		"serial_reference" : "682416PE1A",
		"short_code" : "RBTP",
		"date_created" : "2021-11-10 11:41:53",
		"last_updated" : "2021-11-10 11:41:53"
	},
	{
		"id" : 398896,
		"serial_reference" : "682416PE1A",
		"short_code" : "RBTP",
		"date_created" : "2021-11-10 11:41:53",
		"last_updated" : "2021-11-10 11:41:53"
	},
	{
		"id" : 398912,
		"serial_reference" : "682416PE0A",
		"short_code" : "RBTP",
		"date_created" : "2021-11-10 11:44:25",
		"last_updated" : "2021-11-10 11:44:25"
	},
	{
		"id" : 398920,
		"serial_reference" : "682416PA0A",
		"short_code" : "RBTP",
		"date_created" : "2021-11-10 11:46:27",
		"last_updated" : "2021-11-10 11:46:27"
	},
	{
		"id" : 398928,
		"serial_reference" : "969206PA0A",
		"short_code" : "RBTP",
		"date_created" : "2021-11-10 11:48:20",
		"last_updated" : "2021-11-10 11:48:20"
	},
	{
		"id" : 398936,
		"serial_reference" : "969206PA0A",
		"short_code" : "RBTP",
		"date_created" : "2021-11-10 11:48:20",
		"last_updated" : "2021-11-10 11:48:20"
	},
	{
		"id" : 398944,
		"serial_reference" : "969206PA0A",
		"short_code" : "RBTP",
		"date_created" : "2021-11-10 11:48:20",
		"last_updated" : "2021-11-10 11:48:20"
	},
	{
		"id" : 398952,
		"serial_reference" : "969206PA0A",
		"short_code" : "RBTP",
		"date_created" : "2021-11-10 11:50:28",
		"last_updated" : "2021-11-10 11:50:28"
	},
	{
		"id" : 398960,
		"serial_reference" : "969206PA0A",
		"short_code" : "RBTP",
		"date_created" : "2021-11-10 11:50:28",
		"last_updated" : "2021-11-10 11:50:28"
	},
	{
		"id" : 398968,
		"serial_reference" : "969206PA0A",
		"short_code" : "RBTP",
		"date_created" : "2021-11-10 11:52:15",
		"last_updated" : "2021-11-10 11:52:15"
	},
	{
		"id" : 398976,
		"serial_reference" : "969206PA0A",
		"short_code" : "RBTP",
		"date_created" : "2021-11-10 11:52:15",
		"last_updated" : "2021-11-10 11:52:15"
	},
	{
		"id" : 398984,
		"serial_reference" : "969206PA0A",
		"short_code" : "RBTP",
		"date_created" : "2021-11-10 11:52:16",
		"last_updated" : "2021-11-10 11:52:16"
	},
	{
		"id" : 399072,
		"serial_reference" : "969206PA0A",
		"short_code" : "PTS",
		"date_created" : "2021-11-10 12:11:35",
		"last_updated" : "2021-11-10 12:11:35"
	},
	{
		"id" : 399080,
		"serial_reference" : "969206PA0A",
		"short_code" : "PTS",
		"date_created" : "2021-11-10 12:11:35",
		"last_updated" : "2021-11-10 12:11:35"
	},
	{
		"id" : 399104,
		"serial_reference" : "240106UB2B",
		"short_code" : "CTD",
		"date_created" : "2021-11-10 12:15:37",
		"last_updated" : "2021-11-10 12:15:37"
	},
	{
		"id" : 399128,
		"serial_reference" : "682416PA0A",
		"short_code" : "PTS",
		"date_created" : "2021-11-10 12:18:04",
		"last_updated" : "2021-11-10 12:18:04"
	},
	{
		"id" : 399144,
		"serial_reference" : "240106UD0E",
		"short_code" : "CTD",
		"date_created" : "2021-11-10 12:19:00",
		"last_updated" : "2021-11-10 12:19:00"
	},
	{
		"id" : 399152,
		"serial_reference" : "240106UD0E",
		"short_code" : "CTD",
		"date_created" : "2021-11-10 12:19:27",
		"last_updated" : "2021-11-10 12:19:27"
	},
	{
		"id" : 399160,
		"serial_reference" : "240126WK6A",
		"short_code" : "CTD",
		"date_created" : "2021-11-10 12:26:10",
		"last_updated" : "2021-11-10 12:26:10"
	},
	{
		"id" : 399168,
		"serial_reference" : "969206PA0A",
		"short_code" : "PTS",
		"date_created" : "2021-11-10 12:26:46",
		"last_updated" : "2021-11-10 12:26:46"
	},
	{
		"id" : 399176,
		"serial_reference" : "969206PA0A",
		"short_code" : "PTS",
		"date_created" : "2021-11-10 12:26:46",
		"last_updated" : "2021-11-10 12:26:46"
	},
	{
		"id" : 399184,
		"serial_reference" : "969206PA0A",
		"short_code" : "PTS",
		"date_created" : "2021-11-10 12:33:27",
		"last_updated" : "2021-11-10 12:33:27"
	},
	{
		"id" : 399192,
		"serial_reference" : "969206PA0A",
		"short_code" : "PTS",
		"date_created" : "2021-11-10 12:33:28",
		"last_updated" : "2021-11-10 12:33:28"
	},
	{
		"id" : 399200,
		"serial_reference" : "969206PA0A",
		"short_code" : "PTS",
		"date_created" : "2021-11-10 12:33:28",
		"last_updated" : "2021-11-10 12:33:28"
	},
	{
		"id" : 399216,
		"serial_reference" : "682416PA0A",
		"short_code" : "PTS",
		"date_created" : "2021-11-10 12:58:01",
		"last_updated" : "2021-11-10 12:58:01"
	},
	{
		"id" : 399224,
		"serial_reference" : "969206PA0A",
		"short_code" : "PTS",
		"date_created" : "2021-11-10 13:27:01",
		"last_updated" : "2021-11-10 13:27:01"
	},
	{
		"id" : 399232,
		"serial_reference" : "969206PA0A",
		"short_code" : "PTS",
		"date_created" : "2021-11-10 13:27:02",
		"last_updated" : "2021-11-10 13:27:02"
	},
	{
		"id" : 399240,
		"serial_reference" : "969206PA0A",
		"short_code" : "PTS",
		"date_created" : "2021-11-10 13:27:02",
		"last_updated" : "2021-11-10 13:27:02"
	},
	{
		"id" : 399248,
		"serial_reference" : "240116UA2A",
		"short_code" : "CTD",
		"date_created" : "2021-11-10 13:32:50",
		"last_updated" : "2021-11-10 13:32:50"
	},
	{
		"id" : 399256,
		"serial_reference" : "240106UC1A",
		"short_code" : "CTD",
		"date_created" : "2021-11-10 13:44:08",
		"last_updated" : "2021-11-10 13:44:08"
	},
	{
		"id" : 399264,
		"serial_reference" : "969206PA0A",
		"short_code" : "PTS",
		"date_created" : "2021-11-10 13:47:05",
		"last_updated" : "2021-11-10 13:47:05"
	},
	{
		"id" : 399272,
		"serial_reference" : "969206PA0A",
		"short_code" : "PTS",
		"date_created" : "2021-11-10 13:47:06",
		"last_updated" : "2021-11-10 13:47:06"
	},
	{
		"id" : 399280,
		"serial_reference" : "240116UA1B",
		"short_code" : "CTD",
		"date_created" : "2021-11-10 13:48:13",
		"last_updated" : "2021-11-10 13:48:13"
	},
	{
		"id" : 399288,
		"serial_reference" : "240116uA2B",
		"short_code" : "CTD",
		"date_created" : "2021-11-10 13:53:25",
		"last_updated" : "2021-11-10 13:53:25"
	},
	{
		"id" : 399296,
		"serial_reference" : "240116uA2B",
		"short_code" : "CTD",
		"date_created" : "2021-11-10 13:53:48",
		"last_updated" : "2021-11-10 13:53:48"
	},
	{
		"id" : 399304,
		"serial_reference" : "240116uA2B",
		"short_code" : "CTD",
		"date_created" : "2021-11-10 13:55:40",
		"last_updated" : "2021-11-10 13:55:40"
	},
	{
		"id" : 399312,
		"serial_reference" : "240796ua0a",
		"short_code" : "CTD",
		"date_created" : "2021-11-10 13:59:15",
		"last_updated" : "2021-11-10 13:59:15"
	},
	{
		"id" : 399320,
		"serial_reference" : "240116uA2B",
		"short_code" : "CTD",
		"date_created" : "2021-11-10 13:59:29",
		"last_updated" : "2021-11-10 13:59:29"
	},
	{
		"id" : 399328,
		"serial_reference" : "240116uA2B",
		"short_code" : "CTD",
		"date_created" : "2021-11-10 13:59:40",
		"last_updated" : "2021-11-10 13:59:40"
	},
	{
		"id" : 399336,
		"serial_reference" : "240116uA2B",
		"short_code" : "CTD",
		"date_created" : "2021-11-10 14:02:17",
		"last_updated" : "2021-11-10 14:02:17"
	},
	{
		"id" : 399344,
		"serial_reference" : "240116uA2B",
		"short_code" : "CTD",
		"date_created" : "2021-11-10 14:02:42",
		"last_updated" : "2021-11-10 14:02:42"
	},
	{
		"id" : 399432,
		"serial_reference" : "969206PA0A",
		"short_code" : "PTS",
		"date_created" : "2021-11-10 14:28:03",
		"last_updated" : "2021-11-10 14:28:03"
	},
	{
		"id" : 399440,
		"serial_reference" : "969206PA0A",
		"short_code" : "PTS",
		"date_created" : "2021-11-10 14:28:03",
		"last_updated" : "2021-11-10 14:28:03"
	},
	{
		"id" : 399464,
		"serial_reference" : "682416PE1A",
		"short_code" : "PTS",
		"date_created" : "2021-11-10 14:33:10",
		"last_updated" : "2021-11-10 14:33:10"
	},
	{
		"id" : 399520,
		"serial_reference" : "682416PE0A",
		"short_code" : "PTS",
		"date_created" : "2021-11-10 14:45:31",
		"last_updated" : "2021-11-10 14:45:31"
	},
	{
		"id" : 399528,
		"serial_reference" : "682416PE0A",
		"short_code" : "PTS",
		"date_created" : "2021-11-10 14:45:31",
		"last_updated" : "2021-11-10 14:45:31"
	},
	{
		"id" : 399552,
		"serial_reference" : "682416PA0A",
		"short_code" : "PTS",
		"date_created" : "2021-11-10 14:50:55",
		"last_updated" : "2021-11-10 14:50:55"
	},
	{
		"id" : 399568,
		"serial_reference" : "969206PA0A",
		"short_code" : "PTS",
		"date_created" : "2021-11-10 14:56:25",
		"last_updated" : "2021-11-10 14:56:25"
	},
	{
		"id" : 399576,
		"serial_reference" : "969206PA0A",
		"short_code" : "PTS",
		"date_created" : "2021-11-10 14:56:25",
		"last_updated" : "2021-11-10 14:56:25"
	},
	{
		"id" : 399584,
		"serial_reference" : "969206PA0A",
		"short_code" : "PTS",
		"date_created" : "2021-11-10 14:56:25",
		"last_updated" : "2021-11-10 14:56:25"
	},
	{
		"id" : 399672,
		"serial_reference" : "849035SH1A",
		"short_code" : "PTM",
		"date_created" : "2021-11-10 17:02:08",
		"last_updated" : "2021-11-10 17:02:08"
	},
	{
		"id" : 399680,
		"serial_reference" : "849035SH0A",
		"short_code" : "PTM",
		"date_created" : "2021-11-10 17:02:08",
		"last_updated" : "2021-11-10 17:02:08"
	},
	{
		"id" : 399688,
		"serial_reference" : "849035SH1A",
		"short_code" : "PTM",
		"date_created" : "2021-11-10 17:02:08",
		"last_updated" : "2021-11-10 17:02:08"
	},
	{
		"id" : 399696,
		"serial_reference" : "849355SH2A",
		"short_code" : "PTM",
		"date_created" : "2021-11-10 17:02:08",
		"last_updated" : "2021-11-10 17:02:08"
	},
	{
		"id" : 399704,
		"serial_reference" : "849355SH2A",
		"short_code" : "PTM",
		"date_created" : "2021-11-10 17:02:08",
		"last_updated" : "2021-11-10 17:02:08"
	},
	{
		"id" : 399712,
		"serial_reference" : "849355SH2A",
		"short_code" : "PTM",
		"date_created" : "2021-11-10 17:02:08",
		"last_updated" : "2021-11-10 17:02:08"
	},
	{
		"id" : 399720,
		"serial_reference" : "849355SH2B",
		"short_code" : "PTM",
		"date_created" : "2021-11-10 17:02:08",
		"last_updated" : "2021-11-10 17:02:08"
	},
	{
		"id" : 399728,
		"serial_reference" : "849355SH2B",
		"short_code" : "PTM",
		"date_created" : "2021-11-10 17:02:08",
		"last_updated" : "2021-11-10 17:02:08"
	},
	{
		"id" : 399736,
		"serial_reference" : "849355SH2B",
		"short_code" : "PTM",
		"date_created" : "2021-11-10 17:02:08",
		"last_updated" : "2021-11-10 17:02:08"
	},
	{
		"id" : 399744,
		"serial_reference" : "849035SH0A",
		"short_code" : "PTM",
		"date_created" : "2021-11-10 17:02:08",
		"last_updated" : "2021-11-10 17:02:08"
	},
	{
		"id" : 399880,
		"serial_reference" : "240606UA8A",
		"short_code" : "PTM",
		"date_created" : "2021-11-10 17:10:34",
		"last_updated" : "2021-11-10 17:10:34"
	},
	{
		"id" : 399920,
		"serial_reference" : "4612303W1A     ",
		"short_code" : "PTM",
		"date_created" : "2021-11-10 17:31:30",
		"last_updated" : "2021-11-10 17:31:30"
	},
	{
		"id" : 399944,
		"serial_reference" : "240106UD3D",
		"short_code" : "PTM",
		"date_created" : "2021-11-10 17:50:08",
		"last_updated" : "2021-11-10 17:50:08"
	},
	{
		"id" : 399952,
		"serial_reference" : "240106UD3D",
		"short_code" : "PTM",
		"date_created" : "2021-11-10 17:50:08",
		"last_updated" : "2021-11-10 17:50:08"
	},
	{
		"id" : 399960,
		"serial_reference" : "240106UD3D",
		"short_code" : "PTM",
		"date_created" : "2021-11-10 17:50:09",
		"last_updated" : "2021-11-10 17:50:09"
	},
	{
		"id" : 400024,
		"serial_reference" : "240126WK6A",
		"short_code" : "PTM",
		"date_created" : "2021-11-10 18:26:09",
		"last_updated" : "2021-11-10 18:26:09"
	},
	{
		"id" : 400032,
		"serial_reference" : "240125SJ4B",
		"short_code" : "PTM",
		"date_created" : "2021-11-10 18:26:09",
		"last_updated" : "2021-11-10 18:26:09"
	},
	{
		"id" : 400072,
		"serial_reference" : "240106UD9E",
		"short_code" : "PTM",
		"date_created" : "2021-11-10 18:48:34",
		"last_updated" : "2021-11-10 18:48:34"
	},
	{
		"id" : 400080,
		"serial_reference" : "240115SH0D",
		"short_code" : "PTM",
		"date_created" : "2021-11-10 18:48:34",
		"last_updated" : "2021-11-10 18:48:34"
	},
	{
		"id" : 400120,
		"serial_reference" : "240186UA0A",
		"short_code" : "PTM",
		"date_created" : "2021-11-10 19:09:14",
		"last_updated" : "2021-11-10 19:09:14"
	},
	{
		"id" : 400128,
		"serial_reference" : "0155305131",
		"short_code" : "PTM",
		"date_created" : "2021-11-10 19:18:00",
		"last_updated" : "2021-11-10 19:18:00"
	},
	{
		"id" : 400144,
		"serial_reference" : "6584630F00     ",
		"short_code" : "PTM",
		"date_created" : "2021-11-10 19:34:02",
		"last_updated" : "2021-11-10 19:34:02"
	},
	{
		"id" : 400184,
		"serial_reference" : "0165800551     ",
		"short_code" : "PTM",
		"date_created" : "2021-11-11 06:42:48",
		"last_updated" : "2021-11-11 06:42:48"
	},
	{
		"id" : 400192,
		"serial_reference" : "233000290R",
		"short_code" : "CTD",
		"date_created" : "2021-11-11 07:08:32",
		"last_updated" : "2021-11-11 07:08:32"
	},
	{
		"id" : 400216,
		"serial_reference" : "233000290R",
		"short_code" : "CTD",
		"date_created" : "2021-11-11 07:46:23",
		"last_updated" : "2021-11-11 07:46:23"
	},
	{
		"id" : 400256,
		"serial_reference" : "240126WK5C",
		"short_code" : "PTM",
		"date_created" : "2021-11-11 08:22:29",
		"last_updated" : "2021-11-11 08:22:29"
	},
	{
		"id" : 400264,
		"serial_reference" : "240126WK8d",
		"short_code" : "PTM",
		"date_created" : "2021-11-11 08:22:29",
		"last_updated" : "2021-11-11 08:22:29"
	},
	{
		"id" : 400272,
		"serial_reference" : "240125SN3A",
		"short_code" : "PTM",
		"date_created" : "2021-11-11 08:22:29",
		"last_updated" : "2021-11-11 08:22:29"
	},
	{
		"id" : 400280,
		"serial_reference" : "240125SN3A",
		"short_code" : "PTM",
		"date_created" : "2021-11-11 08:22:29",
		"last_updated" : "2021-11-11 08:22:29"
	},
	{
		"id" : 400368,
		"serial_reference" : "240115SH0D",
		"short_code" : "PTM",
		"date_created" : "2021-11-11 08:50:00",
		"last_updated" : "2021-11-11 08:50:00"
	},
	{
		"id" : 400376,
		"serial_reference" : "240115SH0D",
		"short_code" : "PTM",
		"date_created" : "2021-11-11 08:50:00",
		"last_updated" : "2021-11-11 08:50:00"
	},
	{
		"id" : 400416,
		"serial_reference" : "240125SH6C",
		"short_code" : "CTD",
		"date_created" : "2021-11-11 08:55:15",
		"last_updated" : "2021-11-11 08:55:15"
	},
	{
		"id" : 400424,
		"serial_reference" : "240125SH6C",
		"short_code" : "CTD",
		"date_created" : "2021-11-11 09:01:49",
		"last_updated" : "2021-11-11 09:01:49"
	},
	{
		"id" : 400440,
		"serial_reference" : "295L14NR0A",
		"short_code" : "RBTP",
		"date_created" : "2021-11-11 09:09:53",
		"last_updated" : "2021-11-11 09:09:53"
	},
	{
		"id" : 400448,
		"serial_reference" : "295L14NR0A",
		"short_code" : "RBTP",
		"date_created" : "2021-11-11 09:10:25",
		"last_updated" : "2021-11-11 09:10:25"
	},
	{
		"id" : 400456,
		"serial_reference" : "295L14NR0A",
		"short_code" : "RBTP",
		"date_created" : "2021-11-11 09:10:59",
		"last_updated" : "2021-11-11 09:10:59"
	},
	{
		"id" : 400464,
		"serial_reference" : "295L14NR0A",
		"short_code" : "RBTP",
		"date_created" : "2021-11-11 09:11:33",
		"last_updated" : "2021-11-11 09:11:33"
	},
	{
		"id" : 400472,
		"serial_reference" : "295L14NR0A",
		"short_code" : "RBTP",
		"date_created" : "2021-11-11 09:12:05",
		"last_updated" : "2021-11-11 09:12:05"
	},
	{
		"id" : 400480,
		"serial_reference" : "295L14NR0A",
		"short_code" : "RBTP",
		"date_created" : "2021-11-11 09:12:39",
		"last_updated" : "2021-11-11 09:12:39"
	},
	{
		"id" : 400488,
		"serial_reference" : "295L14NR0A",
		"short_code" : "RBTP",
		"date_created" : "2021-11-11 09:13:13",
		"last_updated" : "2021-11-11 09:13:13"
	},
	{
		"id" : 400496,
		"serial_reference" : "295L14NR0A",
		"short_code" : "RBTP",
		"date_created" : "2021-11-11 09:14:01",
		"last_updated" : "2021-11-11 09:14:01"
	},
	{
		"id" : 400512,
		"serial_reference" : "295L14NR0A",
		"short_code" : "PTS",
		"date_created" : "2021-11-11 09:32:46",
		"last_updated" : "2021-11-11 09:32:46"
	},
	{
		"id" : 400520,
		"serial_reference" : "295L14NR0A",
		"short_code" : "PTS",
		"date_created" : "2021-11-11 09:32:54",
		"last_updated" : "2021-11-11 09:32:54"
	},
	{
		"id" : 400528,
		"serial_reference" : "295L14NR0A",
		"short_code" : "PTS",
		"date_created" : "2021-11-11 09:37:47",
		"last_updated" : "2021-11-11 09:37:47"
	},
	{
		"id" : 400536,
		"serial_reference" : "295L14NR0A",
		"short_code" : "PTS",
		"date_created" : "2021-11-11 09:37:53",
		"last_updated" : "2021-11-11 09:37:53"
	},
	{
		"id" : 400552,
		"serial_reference" : "295L14NR0A",
		"short_code" : "PTS",
		"date_created" : "2021-11-11 09:42:40",
		"last_updated" : "2021-11-11 09:42:40"
	},
	{
		"id" : 400560,
		"serial_reference" : "295L14NR0A",
		"short_code" : "PTS",
		"date_created" : "2021-11-11 09:42:47",
		"last_updated" : "2021-11-11 09:42:47"
	},
	{
		"id" : 400568,
		"serial_reference" : "295L14NR0A",
		"short_code" : "PTS",
		"date_created" : "2021-11-11 09:47:40",
		"last_updated" : "2021-11-11 09:47:40"
	},
	{
		"id" : 400576,
		"serial_reference" : "295L14NR0A",
		"short_code" : "PTS",
		"date_created" : "2021-11-11 09:47:47",
		"last_updated" : "2021-11-11 09:47:47"
	},
	{
		"id" : 400592,
		"serial_reference" : "240125SH6D",
		"short_code" : "CTD",
		"date_created" : "2021-11-11 10:00:06",
		"last_updated" : "2021-11-11 10:00:06"
	},
	{
		"id" : 400600,
		"serial_reference" : "240106UD7B",
		"short_code" : "CTD",
		"date_created" : "2021-11-11 10:25:50",
		"last_updated" : "2021-11-11 10:25:50"
	},
	{
		"id" : 400608,
		"serial_reference" : "240125SH6D",
		"short_code" : "CTD",
		"date_created" : "2021-11-11 10:49:19",
		"last_updated" : "2021-11-11 10:49:19"
	},
	{
		"id" : 400616,
		"serial_reference" : "240606UJ1a",
		"short_code" : "PTM",
		"date_created" : "2021-11-11 10:52:39",
		"last_updated" : "2021-11-11 10:52:39"
	},
	{
		"id" : 400624,
		"serial_reference" : "240106UD8B",
		"short_code" : "PTM",
		"date_created" : "2021-11-11 10:52:39",
		"last_updated" : "2021-11-11 10:52:39"
	},
	{
		"id" : 400648,
		"serial_reference" : "80864HV05A",
		"short_code" : "RBTP",
		"date_created" : "2021-11-11 11:06:12",
		"last_updated" : "2021-11-11 11:06:12"
	},
	{
		"id" : 400656,
		"serial_reference" : "80864HV05A",
		"short_code" : "RBTP",
		"date_created" : "2021-11-11 11:06:13",
		"last_updated" : "2021-11-11 11:06:13"
	},
	{
		"id" : 400664,
		"serial_reference" : "80864HV05A",
		"short_code" : "RBTP",
		"date_created" : "2021-11-11 11:06:13",
		"last_updated" : "2021-11-11 11:06:13"
	},
	{
		"id" : 400704,
		"serial_reference" : "240106UD3D",
		"short_code" : "PTM",
		"date_created" : "2021-11-11 11:40:43",
		"last_updated" : "2021-11-11 11:40:43"
	},
	{
		"id" : 400712,
		"serial_reference" : "240106UD8A",
		"short_code" : "PTM",
		"date_created" : "2021-11-11 11:40:43",
		"last_updated" : "2021-11-11 11:40:43"
	},
	{
		"id" : 400744,
		"serial_reference" : "462717990A     ",
		"short_code" : "PTM",
		"date_created" : "2021-11-11 11:47:36",
		"last_updated" : "2021-11-11 11:47:36"
	},
	{
		"id" : 400784,
		"serial_reference" : "240106UD3D",
		"short_code" : "PTM",
		"date_created" : "2021-11-11 12:03:43",
		"last_updated" : "2021-11-11 12:03:43"
	},
	{
		"id" : 400840,
		"serial_reference" : "240116uA2B",
		"short_code" : "CTD",
		"date_created" : "2021-11-11 12:20:25",
		"last_updated" : "2021-11-11 12:20:25"
	},
	{
		"id" : 400848,
		"serial_reference" : "240116uA2B",
		"short_code" : "CTD",
		"date_created" : "2021-11-11 12:23:53",
		"last_updated" : "2021-11-11 12:23:53"
	},
	{
		"id" : 400864,
		"serial_reference" : "240116uA2B",
		"short_code" : "CTD",
		"date_created" : "2021-11-11 12:27:11",
		"last_updated" : "2021-11-11 12:27:11"
	},
	{
		"id" : 400904,
		"serial_reference" : "240115SH0D",
		"short_code" : "RBTP",
		"date_created" : "2021-11-11 12:35:47",
		"last_updated" : "2021-11-11 12:59:17"
	},
	{
		"id" : 400912,
		"serial_reference" : "240115SH0D",
		"short_code" : "RBTP",
		"date_created" : "2021-11-11 12:35:48",
		"last_updated" : "2021-11-11 12:59:19"
	},
	{
		"id" : 400920,
		"serial_reference" : "240116uA2B",
		"short_code" : "RBTP",
		"date_created" : "2021-11-11 12:36:30",
		"last_updated" : "2021-11-11 12:59:22"
	},
	{
		"id" : 400928,
		"serial_reference" : "240116uA2B",
		"short_code" : "RBTP",
		"date_created" : "2021-11-11 12:36:30",
		"last_updated" : "2021-11-11 12:59:22"
	},
	{
		"id" : 400944,
		"serial_reference" : "240116uA2B",
		"short_code" : "RBTP",
		"date_created" : "2021-11-11 12:37:10",
		"last_updated" : "2021-11-11 12:59:22"
	},
	{
		"id" : 400952,
		"serial_reference" : "240116uA2B",
		"short_code" : "RBTP",
		"date_created" : "2021-11-11 12:37:10",
		"last_updated" : "2021-11-11 12:59:23"
	},
	{
		"id" : 400968,
		"serial_reference" : "240116uA2B",
		"short_code" : "RBTP",
		"date_created" : "2021-11-11 12:37:50",
		"last_updated" : "2021-11-11 12:59:23"
	},
	{
		"id" : 400976,
		"serial_reference" : "240116uA2B",
		"short_code" : "RBTP",
		"date_created" : "2021-11-11 12:37:50",
		"last_updated" : "2021-11-11 12:59:23"
	},
	{
		"id" : 400992,
		"serial_reference" : "240116uA2B",
		"short_code" : "RBTP",
		"date_created" : "2021-11-11 12:38:40",
		"last_updated" : "2021-11-11 12:59:23"
	},
	{
		"id" : 401000,
		"serial_reference" : "240116uA2B",
		"short_code" : "RBTP",
		"date_created" : "2021-11-11 12:38:40",
		"last_updated" : "2021-11-11 12:59:23"
	},
	{
		"id" : 401008,
		"serial_reference" : "295J14NR0A",
		"short_code" : "RBTP",
		"date_created" : "2021-11-11 12:39:19",
		"last_updated" : "2021-11-11 12:39:19"
	},
	{
		"id" : 401016,
		"serial_reference" : "240116uA2B",
		"short_code" : "RBTP",
		"date_created" : "2021-11-11 12:39:23",
		"last_updated" : "2021-11-11 12:59:23"
	},
	{
		"id" : 401024,
		"serial_reference" : "240116uA2B",
		"short_code" : "RBTP",
		"date_created" : "2021-11-11 12:39:23",
		"last_updated" : "2021-11-11 12:59:23"
	},
	{
		"id" : 401032,
		"serial_reference" : "240115SH0D",
		"short_code" : "RBTP",
		"date_created" : "2021-11-11 12:40:00",
		"last_updated" : "2021-11-11 12:59:20"
	},
	{
		"id" : 401040,
		"serial_reference" : "240115SH0D",
		"short_code" : "RBTP",
		"date_created" : "2021-11-11 12:40:00",
		"last_updated" : "2021-11-11 12:59:20"
	},
	{
		"id" : 401048,
		"serial_reference" : "240116uA2B",
		"short_code" : "RBTP",
		"date_created" : "2021-11-11 12:40:34",
		"last_updated" : "2021-11-11 12:59:23"
	},
	{
		"id" : 401056,
		"serial_reference" : "240116uA2B",
		"short_code" : "RBTP",
		"date_created" : "2021-11-11 12:40:35",
		"last_updated" : "2021-11-11 12:59:23"
	},
	{
		"id" : 401072,
		"serial_reference" : "240116uA2B",
		"short_code" : "RBTP",
		"date_created" : "2021-11-11 12:41:11",
		"last_updated" : "2021-11-11 12:59:23"
	},
	{
		"id" : 401080,
		"serial_reference" : "240116uA2B",
		"short_code" : "RBTP",
		"date_created" : "2021-11-11 12:41:12",
		"last_updated" : "2021-11-11 12:59:23"
	},
	{
		"id" : 401088,
		"serial_reference" : "240116uA2B",
		"short_code" : "RBTP",
		"date_created" : "2021-11-11 12:41:42",
		"last_updated" : "2021-11-11 12:59:23"
	},
	{
		"id" : 401096,
		"serial_reference" : "240116uA2B",
		"short_code" : "RBTP",
		"date_created" : "2021-11-11 12:41:43",
		"last_updated" : "2021-11-11 12:59:23"
	},
	{
		"id" : 401104,
		"serial_reference" : "240116uA2B",
		"short_code" : "RBTP",
		"date_created" : "2021-11-11 12:42:20",
		"last_updated" : "2021-11-11 12:59:23"
	},
	{
		"id" : 401112,
		"serial_reference" : "240116uA2B",
		"short_code" : "RBTP",
		"date_created" : "2021-11-11 12:42:20",
		"last_updated" : "2021-11-11 12:59:23"
	},
	{
		"id" : 401128,
		"serial_reference" : "240116uA2B",
		"short_code" : "RBTP",
		"date_created" : "2021-11-11 12:42:55",
		"last_updated" : "2021-11-11 12:59:23"
	},
	{
		"id" : 401136,
		"serial_reference" : "240116uA2B",
		"short_code" : "RBTP",
		"date_created" : "2021-11-11 12:42:55",
		"last_updated" : "2021-11-11 12:59:23"
	},
	{
		"id" : 401144,
		"serial_reference" : "240125SJ4B",
		"short_code" : "RBTP",
		"date_created" : "2021-11-11 12:43:47",
		"last_updated" : "2021-11-11 12:59:28"
	},
	{
		"id" : 401152,
		"serial_reference" : "240116UA2E",
		"short_code" : "RBTD",
		"date_created" : "2021-11-11 12:45:11",
		"last_updated" : "2021-11-11 12:59:26"
	},
	{
		"id" : 401160,
		"serial_reference" : "240126WK6A",
		"short_code" : "RBTD",
		"date_created" : "2021-11-11 12:45:53",
		"last_updated" : "2021-11-11 12:59:30"
	},
	{
		"id" : 401168,
		"serial_reference" : "240116UA1B",
		"short_code" : "RBTD",
		"date_created" : "2021-11-11 12:46:27",
		"last_updated" : "2021-11-11 12:59:21"
	},
	{
		"id" : 401176,
		"serial_reference" : "240126WK6A",
		"short_code" : "RBTD",
		"date_created" : "2021-11-11 12:46:59",
		"last_updated" : "2021-11-11 12:59:30"
	},
	{
		"id" : 401192,
		"serial_reference" : "240116UA2E",
		"short_code" : "RBTD",
		"date_created" : "2021-11-11 12:47:47",
		"last_updated" : "2021-11-11 12:59:26"
	},
	{
		"id" : 401200,
		"serial_reference" : "240126WK6D",
		"short_code" : "RBTD",
		"date_created" : "2021-11-11 12:48:17",
		"last_updated" : "2021-11-11 12:48:17"
	},
	{
		"id" : 401208,
		"serial_reference" : "240116UA2E",
		"short_code" : "RBTD",
		"date_created" : "2021-11-11 12:49:04",
		"last_updated" : "2021-11-11 12:59:26"
	},
	{
		"id" : 401384,
		"serial_reference" : "295J14NR0A",
		"short_code" : "PTS",
		"date_created" : "2021-11-11 13:46:29",
		"last_updated" : "2021-11-11 13:46:29"
	},
	{
		"id" : 401392,
		"serial_reference" : "240116uA2B",
		"short_code" : "PTS",
		"date_created" : "2021-11-11 13:50:23",
		"last_updated" : "2021-11-11 13:50:23"
	},
	{
		"id" : 401400,
		"serial_reference" : "240116uA2B",
		"short_code" : "PTS",
		"date_created" : "2021-11-11 13:50:23",
		"last_updated" : "2021-11-11 13:50:23"
	},
	{
		"id" : 401408,
		"serial_reference" : "240116uA2B",
		"short_code" : "PTS",
		"date_created" : "2021-11-11 13:50:33",
		"last_updated" : "2021-11-11 13:50:33"
	},
	{
		"id" : 401416,
		"serial_reference" : "240116uA2B",
		"short_code" : "PTS",
		"date_created" : "2021-11-11 13:50:33",
		"last_updated" : "2021-11-11 13:50:33"
	},
	{
		"id" : 401440,
		"serial_reference" : "240116uA2B",
		"short_code" : "PTS",
		"date_created" : "2021-11-11 13:59:01",
		"last_updated" : "2021-11-11 13:59:01"
	},
	{
		"id" : 401448,
		"serial_reference" : "240116uA2B",
		"short_code" : "PTS",
		"date_created" : "2021-11-11 13:59:01",
		"last_updated" : "2021-11-11 13:59:01"
	},
	{
		"id" : 401456,
		"serial_reference" : "240116uA2B",
		"short_code" : "PTS",
		"date_created" : "2021-11-11 14:00:48",
		"last_updated" : "2021-11-11 14:00:48"
	},
	{
		"id" : 401464,
		"serial_reference" : "240116uA2B",
		"short_code" : "PTS",
		"date_created" : "2021-11-11 14:00:48",
		"last_updated" : "2021-11-11 14:00:48"
	},
	{
		"id" : 401512,
		"serial_reference" : "240115SH0D",
		"short_code" : "PTS",
		"date_created" : "2021-11-11 14:07:53",
		"last_updated" : "2021-11-11 14:07:53"
	},
	{
		"id" : 401544,
		"serial_reference" : "240116uA2B",
		"short_code" : "PTS",
		"date_created" : "2021-11-11 14:10:11",
		"last_updated" : "2021-11-11 14:10:11"
	},
	{
		"id" : 401552,
		"serial_reference" : "240116uA2B",
		"short_code" : "PTS",
		"date_created" : "2021-11-11 14:10:11",
		"last_updated" : "2021-11-11 14:10:11"
	},
	{
		"id" : 401576,
		"serial_reference" : "240116uA2B",
		"short_code" : "PTS",
		"date_created" : "2021-11-11 14:16:30",
		"last_updated" : "2021-11-11 14:16:30"
	},
	{
		"id" : 401584,
		"serial_reference" : "240116uA2B",
		"short_code" : "PTS",
		"date_created" : "2021-11-11 14:16:30",
		"last_updated" : "2021-11-11 14:16:30"
	},
	{
		"id" : 401592,
		"serial_reference" : "240125SJ4B",
		"short_code" : "PTS",
		"date_created" : "2021-11-11 14:18:58",
		"last_updated" : "2021-11-11 14:18:58"
	},
	{
		"id" : 401600,
		"serial_reference" : "240126WK9B",
		"short_code" : "CTS",
		"date_created" : "2021-11-11 14:21:23",
		"last_updated" : "2021-11-11 14:21:23"
	},
	{
		"id" : 401656,
		"serial_reference" : "240116uA2B",
		"short_code" : "PTS",
		"date_created" : "2021-11-11 14:27:27",
		"last_updated" : "2021-11-11 14:27:27"
	},
	{
		"id" : 401664,
		"serial_reference" : "240116uA2B",
		"short_code" : "PTS",
		"date_created" : "2021-11-11 14:27:27",
		"last_updated" : "2021-11-11 14:27:27"
	},
	{
		"id" : 401672,
		"serial_reference" : "240116uA2B",
		"short_code" : "PTS",
		"date_created" : "2021-11-11 14:27:27",
		"last_updated" : "2021-11-11 14:27:27"
	},
	{
		"id" : 401680,
		"serial_reference" : "240116uA2B",
		"short_code" : "PTS",
		"date_created" : "2021-11-11 14:29:04",
		"last_updated" : "2021-11-11 14:29:04"
	},
	{
		"id" : 401688,
		"serial_reference" : "240116uA2B",
		"short_code" : "PTS",
		"date_created" : "2021-11-11 14:29:04",
		"last_updated" : "2021-11-11 14:29:04"
	},
	{
		"id" : 401720,
		"serial_reference" : "240115SH0D",
		"short_code" : "PTS",
		"date_created" : "2021-11-11 14:34:18",
		"last_updated" : "2021-11-11 14:34:18"
	},
	{
		"id" : 401728,
		"serial_reference" : "240115SH0D",
		"short_code" : "PTS",
		"date_created" : "2021-11-11 14:34:18",
		"last_updated" : "2021-11-11 14:34:18"
	},
	{
		"id" : 401752,
		"serial_reference" : "240116uA2B",
		"short_code" : "PTS",
		"date_created" : "2021-11-11 14:39:11",
		"last_updated" : "2021-11-11 14:39:11"
	},
	{
		"id" : 401760,
		"serial_reference" : "240116uA2B",
		"short_code" : "PTS",
		"date_created" : "2021-11-11 14:39:11",
		"last_updated" : "2021-11-11 14:39:11"
	},
	{
		"id" : 401784,
		"serial_reference" : "240116uA2B",
		"short_code" : "PTS",
		"date_created" : "2021-11-11 14:42:11",
		"last_updated" : "2021-11-11 14:42:11"
	},
	{
		"id" : 401792,
		"serial_reference" : "240116uA2B",
		"short_code" : "PTS",
		"date_created" : "2021-11-11 14:42:11",
		"last_updated" : "2021-11-11 14:42:11"
	},
	{
		"id" : 401800,
		"serial_reference" : "240116UA2D",
		"short_code" : "CTD",
		"date_created" : "2021-11-11 14:46:21",
		"last_updated" : "2021-11-11 14:46:21"
	},
	{
		"id" : 401808,
		"serial_reference" : "240116UA2E",
		"short_code" : "CTD",
		"date_created" : "2021-11-11 14:46:47",
		"last_updated" : "2021-11-11 14:46:47"
	},
	{
		"id" : 401816,
		"serial_reference" : "240116UA2E",
		"short_code" : "CTD",
		"date_created" : "2021-11-11 14:47:11",
		"last_updated" : "2021-11-11 14:47:11"
	},
	{
		"id" : 401824,
		"serial_reference" : "240116UA2D",
		"short_code" : "CTD",
		"date_created" : "2021-11-11 14:47:46",
		"last_updated" : "2021-11-11 14:47:46"
	},
	{
		"id" : 401832,
		"serial_reference" : "240106UD8B",
		"short_code" : "CTD",
		"date_created" : "2021-11-11 14:58:26",
		"last_updated" : "2021-11-11 14:58:26"
	},
	{
		"id" : 402024,
		"serial_reference" : "240126WK6A",
		"short_code" : "CTD",
		"date_created" : "2021-11-11 16:03:05",
		"last_updated" : "2021-11-11 16:03:05"
	},
	{
		"id" : 402064,
		"serial_reference" : "240106UD9E",
		"short_code" : "PTM",
		"date_created" : "2021-11-11 16:47:59",
		"last_updated" : "2021-11-11 16:47:59"
	},
	{
		"id" : 402096,
		"serial_reference" : "240606UJ1a",
		"short_code" : "PTM",
		"date_created" : "2021-11-11 17:17:17",
		"last_updated" : "2021-11-11 17:17:17"
	},
	{
		"id" : 402104,
		"serial_reference" : "240106UD7B",
		"short_code" : "PTM",
		"date_created" : "2021-11-11 17:17:17",
		"last_updated" : "2021-11-11 17:17:17"
	},
	{
		"id" : 402128,
		"serial_reference" : "240126WK9d",
		"short_code" : "PTM",
		"date_created" : "2021-11-11 17:26:21",
		"last_updated" : "2021-11-11 17:26:21"
	},
	{
		"id" : 402136,
		"serial_reference" : "240126WK6A",
		"short_code" : "PTM",
		"date_created" : "2021-11-11 17:26:21",
		"last_updated" : "2021-11-11 17:26:21"
	},
	{
		"id" : 402160,
		"serial_reference" : "240126WK8d",
		"short_code" : "CTS",
		"date_created" : "2021-11-11 17:26:56",
		"last_updated" : "2021-11-11 17:26:56"
	},
	{
		"id" : 402168,
		"serial_reference" : "80864HV05A",
		"short_code" : "PTS",
		"date_created" : "2021-11-11 17:28:24",
		"last_updated" : "2021-11-11 17:28:24"
	},
	{
		"id" : 402176,
		"serial_reference" : "80864HV05A",
		"short_code" : "PTS",
		"date_created" : "2021-11-11 17:28:24",
		"last_updated" : "2021-11-11 17:28:24"
	},
	{
		"id" : 402184,
		"serial_reference" : "80864HV05A",
		"short_code" : "PTS",
		"date_created" : "2021-11-11 17:28:24",
		"last_updated" : "2021-11-11 17:28:24"
	},
	{
		"id" : 402208,
		"serial_reference" : "240126WK6A",
		"short_code" : "CTS",
		"date_created" : "2021-11-11 17:35:16",
		"last_updated" : "2021-11-11 17:35:16"
	},
	{
		"id" : 402248,
		"serial_reference" : "240115SH0D",
		"short_code" : "PTM",
		"date_created" : "2021-11-11 17:50:51",
		"last_updated" : "2021-11-11 17:50:51"
	},
	{
		"id" : 402296,
		"serial_reference" : "1643956S0A     ",
		"short_code" : "PTM",
		"date_created" : "2021-11-11 18:22:17",
		"last_updated" : "2021-11-11 18:22:17"
	},
	{
		"id" : 402312,
		"serial_reference" : "240335SH0A",
		"short_code" : "PTM",
		"date_created" : "2021-11-11 18:44:29",
		"last_updated" : "2021-11-11 18:44:29"
	},
	{
		"id" : 402336,
		"serial_reference" : "4612303W1A     ",
		"short_code" : "PTM",
		"date_created" : "2021-11-11 19:03:25",
		"last_updated" : "2021-11-11 19:03:25"
	},
	{
		"id" : 402376,
		"serial_reference" : "240126WK6C",
		"short_code" : "PTM",
		"date_created" : "2021-11-11 22:36:17",
		"last_updated" : "2021-11-11 22:36:17"
	},
	{
		"id" : 402384,
		"serial_reference" : "240125SJ4B",
		"short_code" : "PTM",
		"date_created" : "2021-11-11 22:36:17",
		"last_updated" : "2021-11-11 22:36:17"
	},
	{
		"id" : 402472,
		"serial_reference" : "240125SJ4B",
		"short_code" : "PTM",
		"date_created" : "2021-11-12 07:29:31",
		"last_updated" : "2021-11-12 07:29:31"
	},
	{
		"id" : 402528,
		"serial_reference" : "240115SH0D",
		"short_code" : "PTM",
		"date_created" : "2021-11-12 07:47:51",
		"last_updated" : "2021-11-12 07:47:51"
	},
	{
		"id" : 402616,
		"serial_reference" : "240106UD3C",
		"short_code" : "PTM",
		"date_created" : "2021-11-12 08:43:47",
		"last_updated" : "2021-11-12 08:43:47"
	},
	{
		"id" : 402632,
		"serial_reference" : "240126WK6C",
		"short_code" : "CTD",
		"date_created" : "2021-11-12 08:46:27",
		"last_updated" : "2021-11-12 08:46:27"
	},
	{
		"id" : 402648,
		"serial_reference" : "240106UD6E",
		"short_code" : "CTD",
		"date_created" : "2021-11-12 09:03:44",
		"last_updated" : "2021-11-12 09:03:44"
	},
	{
		"id" : 402664,
		"serial_reference" : "240126WK6A",
		"short_code" : "CTD",
		"date_created" : "2021-11-12 09:07:36",
		"last_updated" : "2021-11-12 09:07:36"
	},
	{
		"id" : 402672,
		"serial_reference" : "295L14NR0A",
		"short_code" : "PTM",
		"date_created" : "2021-11-12 09:11:06",
		"last_updated" : "2021-11-12 09:11:06"
	},
	{
		"id" : 402680,
		"serial_reference" : "295L14NR0A",
		"short_code" : "PTM",
		"date_created" : "2021-11-12 09:11:06",
		"last_updated" : "2021-11-12 09:11:06"
	},
	{
		"id" : 402688,
		"serial_reference" : "295L14NR0A",
		"short_code" : "PTM",
		"date_created" : "2021-11-12 09:11:06",
		"last_updated" : "2021-11-12 09:11:06"
	},
	{
		"id" : 402696,
		"serial_reference" : "295L14NR0A",
		"short_code" : "PTM",
		"date_created" : "2021-11-12 09:11:06",
		"last_updated" : "2021-11-12 09:11:06"
	},
	{
		"id" : 402704,
		"serial_reference" : "295L14NR0A",
		"short_code" : "PTM",
		"date_created" : "2021-11-12 09:11:06",
		"last_updated" : "2021-11-12 09:11:06"
	},
	{
		"id" : 402712,
		"serial_reference" : "295L14NR0A",
		"short_code" : "PTM",
		"date_created" : "2021-11-12 09:11:06",
		"last_updated" : "2021-11-12 09:11:06"
	},
	{
		"id" : 402720,
		"serial_reference" : "295L14NR0A",
		"short_code" : "PTM",
		"date_created" : "2021-11-12 09:11:06",
		"last_updated" : "2021-11-12 09:11:06"
	},
	{
		"id" : 402728,
		"serial_reference" : "295L14NR0A",
		"short_code" : "PTM",
		"date_created" : "2021-11-12 09:11:06",
		"last_updated" : "2021-11-12 09:11:06"
	},
	{
		"id" : 402736,
		"serial_reference" : "295L14NR0A",
		"short_code" : "PTM",
		"date_created" : "2021-11-12 09:11:06",
		"last_updated" : "2021-11-12 09:11:06"
	},
	{
		"id" : 402744,
		"serial_reference" : "295L14NR0A",
		"short_code" : "PTM",
		"date_created" : "2021-11-12 09:11:06",
		"last_updated" : "2021-11-12 09:11:06"
	},
	{
		"id" : 402752,
		"serial_reference" : "295L14NR0A",
		"short_code" : "PTM",
		"date_created" : "2021-11-12 09:11:06",
		"last_updated" : "2021-11-12 09:11:06"
	},
	{
		"id" : 402760,
		"serial_reference" : "295L14NR0A",
		"short_code" : "PTM",
		"date_created" : "2021-11-12 09:11:06",
		"last_updated" : "2021-11-12 09:11:06"
	},
	{
		"id" : 402768,
		"serial_reference" : "295L14NR0A",
		"short_code" : "PTM",
		"date_created" : "2021-11-12 09:11:06",
		"last_updated" : "2021-11-12 09:11:06"
	},
	{
		"id" : 402776,
		"serial_reference" : "295L14NR0A",
		"short_code" : "PTM",
		"date_created" : "2021-11-12 09:11:06",
		"last_updated" : "2021-11-12 09:11:06"
	},
	{
		"id" : 402784,
		"serial_reference" : "295L14NR0A",
		"short_code" : "PTM",
		"date_created" : "2021-11-12 09:11:06",
		"last_updated" : "2021-11-12 09:11:06"
	},
	{
		"id" : 402792,
		"serial_reference" : "295L14NR0A",
		"short_code" : "PTM",
		"date_created" : "2021-11-12 09:11:06",
		"last_updated" : "2021-11-12 09:11:06"
	},
	{
		"id" : 402800,
		"serial_reference" : "295L14NR0A",
		"short_code" : "PTM",
		"date_created" : "2021-11-12 09:11:06",
		"last_updated" : "2021-11-12 09:11:06"
	},
	{
		"id" : 402808,
		"serial_reference" : "295L14NR0A",
		"short_code" : "PTM",
		"date_created" : "2021-11-12 09:11:06",
		"last_updated" : "2021-11-12 09:11:06"
	},
	{
		"id" : 402816,
		"serial_reference" : "295L14NR0A",
		"short_code" : "PTM",
		"date_created" : "2021-11-12 09:11:06",
		"last_updated" : "2021-11-12 09:11:06"
	},
	{
		"id" : 403024,
		"serial_reference" : "240126WK6A",
		"short_code" : "CTD",
		"date_created" : "2021-11-12 09:26:12",
		"last_updated" : "2021-11-12 09:26:12"
	},
	{
		"id" : 403032,
		"serial_reference" : "240335SH0A",
		"short_code" : "PTM",
		"date_created" : "2021-11-12 09:30:19",
		"last_updated" : "2021-11-12 09:30:19"
	},
	{
		"id" : 403040,
		"serial_reference" : "240796ua0a",
		"short_code" : "CTM",
		"date_created" : "2021-11-12 09:33:06",
		"last_updated" : "2021-11-12 09:33:06"
	},
	{
		"id" : 403072,
		"serial_reference" : "240106ub9d",
		"short_code" : "PTM",
		"date_created" : "2021-11-12 09:56:59",
		"last_updated" : "2021-11-12 09:56:59"
	},
	{
		"id" : 403080,
		"serial_reference" : "240106ub9d",
		"short_code" : "PTM",
		"date_created" : "2021-11-12 09:56:59",
		"last_updated" : "2021-11-12 09:56:59"
	},
	{
		"id" : 403112,
		"serial_reference" : "240126WK6A",
		"short_code" : "CTD",
		"date_created" : "2021-11-12 10:02:44",
		"last_updated" : "2021-11-12 10:02:44"
	},
	{
		"id" : 403120,
		"serial_reference" : "240106UD6E",
		"short_code" : "CTD",
		"date_created" : "2021-11-12 10:29:16",
		"last_updated" : "2021-11-12 10:29:16"
	},
	{
		"id" : 403128,
		"serial_reference" : "240126WK6A",
		"short_code" : "CTD",
		"date_created" : "2021-11-12 10:33:32",
		"last_updated" : "2021-11-12 10:33:32"
	},
	{
		"id" : 403144,
		"serial_reference" : "240106UD8B",
		"short_code" : "CTD",
		"date_created" : "2021-11-12 10:53:57",
		"last_updated" : "2021-11-12 10:53:57"
	},
	{
		"id" : 403176,
		"serial_reference" : "240106UC1D",
		"short_code" : "CTM",
		"date_created" : "2021-11-12 11:20:30",
		"last_updated" : "2021-11-12 11:20:30"
	},
	{
		"id" : 403216,
		"serial_reference" : "240606UA1A",
		"short_code" : "CTM",
		"date_created" : "2021-11-12 11:44:38",
		"last_updated" : "2021-11-12 11:44:38"
	},
	{
		"id" : 403240,
		"serial_reference" : "240106UD6E",
		"short_code" : "CTD",
		"date_created" : "2021-11-12 11:49:43",
		"last_updated" : "2021-11-12 11:49:43"
	},
	{
		"id" : 403264,
		"serial_reference" : "240106UD6E",
		"short_code" : "CTD",
		"date_created" : "2021-11-12 11:56:40",
		"last_updated" : "2021-11-12 11:56:40"
	},
	{
		"id" : 403360,
		"serial_reference" : "682416PA0A",
		"short_code" : "PTM",
		"date_created" : "2021-11-12 12:19:14",
		"last_updated" : "2021-11-12 12:19:14"
	},
	{
		"id" : 403368,
		"serial_reference" : "682416PA0A",
		"short_code" : "PTM",
		"date_created" : "2021-11-12 12:19:14",
		"last_updated" : "2021-11-12 12:19:14"
	},
	{
		"id" : 403376,
		"serial_reference" : "682416PA0A",
		"short_code" : "PTM",
		"date_created" : "2021-11-12 12:19:14",
		"last_updated" : "2021-11-12 12:19:14"
	},
	{
		"id" : 403384,
		"serial_reference" : "682416PA0A",
		"short_code" : "PTM",
		"date_created" : "2021-11-12 12:19:14",
		"last_updated" : "2021-11-12 12:19:14"
	},
	{
		"id" : 403392,
		"serial_reference" : "682416PA1A",
		"short_code" : "PTM",
		"date_created" : "2021-11-12 12:19:14",
		"last_updated" : "2021-11-12 12:19:14"
	},
	{
		"id" : 403400,
		"serial_reference" : "682416PA1A",
		"short_code" : "PTM",
		"date_created" : "2021-11-12 12:19:14",
		"last_updated" : "2021-11-12 12:19:14"
	},
	{
		"id" : 403408,
		"serial_reference" : "682416PA1A",
		"short_code" : "PTM",
		"date_created" : "2021-11-12 12:19:14",
		"last_updated" : "2021-11-12 12:19:14"
	},
	{
		"id" : 403416,
		"serial_reference" : "682416PA1A",
		"short_code" : "PTM",
		"date_created" : "2021-11-12 12:19:14",
		"last_updated" : "2021-11-12 12:19:14"
	},
	{
		"id" : 403424,
		"serial_reference" : "682416PE1A",
		"short_code" : "PTM",
		"date_created" : "2021-11-12 12:19:14",
		"last_updated" : "2021-11-12 12:19:14"
	},
	{
		"id" : 403432,
		"serial_reference" : "682416PE1A",
		"short_code" : "PTM",
		"date_created" : "2021-11-12 12:19:14",
		"last_updated" : "2021-11-12 12:19:14"
	},
	{
		"id" : 403440,
		"serial_reference" : "682416PE1A",
		"short_code" : "PTM",
		"date_created" : "2021-11-12 12:19:14",
		"last_updated" : "2021-11-12 12:19:14"
	},
	{
		"id" : 403448,
		"serial_reference" : "682416PE0A",
		"short_code" : "PTM",
		"date_created" : "2021-11-12 12:19:14",
		"last_updated" : "2021-11-12 12:19:14"
	},
	{
		"id" : 403456,
		"serial_reference" : "682416PE0A",
		"short_code" : "PTM",
		"date_created" : "2021-11-12 12:19:14",
		"last_updated" : "2021-11-12 12:19:14"
	},
	{
		"id" : 403464,
		"serial_reference" : "682416PE0A",
		"short_code" : "PTM",
		"date_created" : "2021-11-12 12:19:14",
		"last_updated" : "2021-11-12 12:19:14"
	},
	{
		"id" : 403472,
		"serial_reference" : "682416PE0A",
		"short_code" : "PTM",
		"date_created" : "2021-11-12 12:19:14",
		"last_updated" : "2021-11-12 12:19:14"
	},
	{
		"id" : 403480,
		"serial_reference" : "682416PE0A",
		"short_code" : "PTM",
		"date_created" : "2021-11-12 12:19:14",
		"last_updated" : "2021-11-12 12:19:14"
	},
	{
		"id" : 403488,
		"serial_reference" : "682416PE0A",
		"short_code" : "PTM",
		"date_created" : "2021-11-12 12:19:14",
		"last_updated" : "2021-11-12 12:19:14"
	},
	{
		"id" : 403496,
		"serial_reference" : "682416PE0A",
		"short_code" : "PTM",
		"date_created" : "2021-11-12 12:19:14",
		"last_updated" : "2021-11-12 12:19:14"
	},
	{
		"id" : 403504,
		"serial_reference" : "682416PE0A",
		"short_code" : "PTM",
		"date_created" : "2021-11-12 12:19:14",
		"last_updated" : "2021-11-12 12:19:14"
	},
	{
		"id" : 403512,
		"serial_reference" : "682416PE0A",
		"short_code" : "PTM",
		"date_created" : "2021-11-12 12:19:14",
		"last_updated" : "2021-11-12 12:19:14"
	},
	{
		"id" : 403520,
		"serial_reference" : "682416PE0A",
		"short_code" : "PTM",
		"date_created" : "2021-11-12 12:19:14",
		"last_updated" : "2021-11-12 12:19:14"
	},
	{
		"id" : 403528,
		"serial_reference" : "682416PE0A",
		"short_code" : "PTM",
		"date_created" : "2021-11-12 12:19:14",
		"last_updated" : "2021-11-12 12:19:14"
	},
	{
		"id" : 403536,
		"serial_reference" : "969206PA0A",
		"short_code" : "PTM",
		"date_created" : "2021-11-12 12:19:15",
		"last_updated" : "2021-11-12 12:19:15"
	},
	{
		"id" : 403544,
		"serial_reference" : "969206PA0A",
		"short_code" : "PTM",
		"date_created" : "2021-11-12 12:19:15",
		"last_updated" : "2021-11-12 12:19:15"
	},
	{
		"id" : 403552,
		"serial_reference" : "969206PA0A",
		"short_code" : "PTM",
		"date_created" : "2021-11-12 12:19:15",
		"last_updated" : "2021-11-12 12:19:15"
	},
	{
		"id" : 403560,
		"serial_reference" : "969206PA0A",
		"short_code" : "PTM",
		"date_created" : "2021-11-12 12:19:15",
		"last_updated" : "2021-11-12 12:19:15"
	},
	{
		"id" : 403568,
		"serial_reference" : "969206PA0A",
		"short_code" : "PTM",
		"date_created" : "2021-11-12 12:19:15",
		"last_updated" : "2021-11-12 12:19:15"
	},
	{
		"id" : 403576,
		"serial_reference" : "969206PA0A",
		"short_code" : "PTM",
		"date_created" : "2021-11-12 12:19:15",
		"last_updated" : "2021-11-12 12:19:15"
	},
	{
		"id" : 403584,
		"serial_reference" : "969206PA0A",
		"short_code" : "PTM",
		"date_created" : "2021-11-12 12:19:15",
		"last_updated" : "2021-11-12 12:19:15"
	},
	{
		"id" : 403592,
		"serial_reference" : "969206PA0A",
		"short_code" : "PTM",
		"date_created" : "2021-11-12 12:19:15",
		"last_updated" : "2021-11-12 12:19:15"
	},
	{
		"id" : 403600,
		"serial_reference" : "969206PA0A",
		"short_code" : "PTM",
		"date_created" : "2021-11-12 12:19:15",
		"last_updated" : "2021-11-12 12:19:15"
	},
	{
		"id" : 403608,
		"serial_reference" : "969206PA0A",
		"short_code" : "PTM",
		"date_created" : "2021-11-12 12:19:15",
		"last_updated" : "2021-11-12 12:19:15"
	},
	{
		"id" : 403616,
		"serial_reference" : "969206PA0A",
		"short_code" : "PTM",
		"date_created" : "2021-11-12 12:19:15",
		"last_updated" : "2021-11-12 12:19:15"
	},
	{
		"id" : 403624,
		"serial_reference" : "969206PA0A",
		"short_code" : "PTM",
		"date_created" : "2021-11-12 12:19:15",
		"last_updated" : "2021-11-12 12:19:15"
	},
	{
		"id" : 403632,
		"serial_reference" : "969206PA0A",
		"short_code" : "PTM",
		"date_created" : "2021-11-12 12:19:15",
		"last_updated" : "2021-11-12 12:19:15"
	},
	{
		"id" : 403640,
		"serial_reference" : "969206PA0A",
		"short_code" : "PTM",
		"date_created" : "2021-11-12 12:19:15",
		"last_updated" : "2021-11-12 12:19:15"
	},
	{
		"id" : 403648,
		"serial_reference" : "969206PA0A",
		"short_code" : "PTM",
		"date_created" : "2021-11-12 12:19:15",
		"last_updated" : "2021-11-12 12:19:15"
	},
	{
		"id" : 403656,
		"serial_reference" : "969206PA0A",
		"short_code" : "PTM",
		"date_created" : "2021-11-12 12:19:15",
		"last_updated" : "2021-11-12 12:19:15"
	},
	{
		"id" : 403664,
		"serial_reference" : "969206PA0A",
		"short_code" : "PTM",
		"date_created" : "2021-11-12 12:19:15",
		"last_updated" : "2021-11-12 12:19:15"
	},
	{
		"id" : 403672,
		"serial_reference" : "969206PA0A",
		"short_code" : "PTM",
		"date_created" : "2021-11-12 12:19:15",
		"last_updated" : "2021-11-12 12:19:15"
	},
	{
		"id" : 403680,
		"serial_reference" : "969206PA0A",
		"short_code" : "PTM",
		"date_created" : "2021-11-12 12:19:15",
		"last_updated" : "2021-11-12 12:19:15"
	},
	{
		"id" : 403688,
		"serial_reference" : "969206PA0A",
		"short_code" : "PTM",
		"date_created" : "2021-11-12 12:19:15",
		"last_updated" : "2021-11-12 12:19:15"
	},
	{
		"id" : 403696,
		"serial_reference" : "969206PA0A",
		"short_code" : "PTM",
		"date_created" : "2021-11-12 12:19:15",
		"last_updated" : "2021-11-12 12:19:15"
	},
	{
		"id" : 404448,
		"serial_reference" : "240796ua0a",
		"short_code" : "CTD",
		"date_created" : "2021-11-12 12:30:37",
		"last_updated" : "2021-11-12 12:30:37"
	},
	{
		"id" : 404456,
		"serial_reference" : "240796ua0a",
		"short_code" : "CTD",
		"date_created" : "2021-11-12 12:30:56",
		"last_updated" : "2021-11-12 12:30:56"
	},
	{
		"id" : 404480,
		"serial_reference" : "240106UE0B",
		"short_code" : "PTM",
		"date_created" : "2021-11-12 12:32:28",
		"last_updated" : "2021-11-12 12:32:28"
	},
	{
		"id" : 404536,
		"serial_reference" : "240106UD6E",
		"short_code" : "CTD",
		"date_created" : "2021-11-12 12:50:47",
		"last_updated" : "2021-11-12 12:50:47"
	}
]
